Workbook

Sheet Dashboard
A1: Dashboard de seguimiento y evaluación del Plan de Efectividad
A2: BGU · Ciclo académico 01/09/2025 – 31/08/2026
A4: Seleccione el corte para lectura del dashboard | E4: C1 - Diciembre
B6: Total indicadores | E6: Mensuales | H6: Semestrales | K6: Anuales
B7: =COUNTA('Indicadores Master'!$D$2:$D$65) -> 64 | E7: =COUNTIF('Indicadores Master'!$K$2:$K$65,"Mensual") -> 2 | H7: =COUNTIF('Indicadores Master'!$K$2:$K$65,"Semestral") -> 3 | K7: =COUNTIF('Indicadores Master'!$K$2:$K$65,"Anual") -> 59
A11: Resumen del corte seleccionado | D11: Cumplimiento por dimensión (según corte seleccionado) | J11: Distribución del juicio evaluativo
A13: Indicador | B13: Valor | D13: Dimensión | E13: Cumple | F13: En riesgo | G13: No cumple | H13: Pendiente
A14: Indicadores con juicio "Cumple" | B14: =IF($E$4="C1 - Diciembre",COUNTIF('Evaluación Cortes Semestrales'!$I$5:$I$68,"Cumple"),IF($E$4="C2 - Abril",COUNTIF('Evaluación Cortes Semestrales'!$P$5:$P$68,"Cumple"),COUNTIF('Evaluación Cortes Semestrales'!$W$5:$W$68,"Cumple"))) -> 3 | D14: 1. Portafolio Académico | E14: =IF($E$4="C1 - Diciembre",SUMPRODUCT(('Evaluación Cortes Semestrales'!$B$5:$B$68=D14)*('Evaluación Cortes Semestrales'!$I$5:$I$68="Cumple")),IF($E$4="C2 - Abril",SUMPRODUCT(('Evaluación Cortes Semestrales'!$B$5:$B$68=D14)*('Evaluación Cortes Semestrales'!$P$5:$P$68="Cumple")),SUMPRODUCT(('Evaluación Cortes Semestrales'!$B$5:$B$68=D14)*('Evaluación Cortes Semestrales'!$W$5:$W$68="Cumple")))) -> 0 | F14: =IF($E$4="C1 - Diciembre",SUMPRODUCT(('Evaluación Cortes Semestrales'!$B$5:$B$68=D14)*('Evaluación Cortes Semestrales'!$I$5:$I$68="En riesgo")),IF($E$4="C2 - Abril",SUMPRODUCT(('Evaluación Cortes Semestrales'!$B$5:$B$68=D14)*('Evaluación Cortes Semestrales'!$P$5:$P$68="En riesgo")),SUMPRODUCT(('Evaluación Cortes Semestrales'!$B$5:$B$68=D14)*('Evaluación Cortes Semestrales'!$W$5:$W$68="En riesgo")))) -> 0 | G14: =IF($E$4="C1 - Diciembre",SUMPRODUCT(('Evaluación Cortes Semestrales'!$B$5:$B$68=D14)*('Evaluación Cortes Semestrales'!$I$5:$I$68="No cumple")),IF($E$4="C2 - Abril",SUMPRODUCT(('Evaluación Cortes Semestrales'!$B$5:$B$68=D14)*('Evaluación Cortes Semestrales'!$P$5:$P$68="No cumple")),SUMPRODUCT(('Evaluación Cortes Semestrales'!$B$5:$B$68=D14)*('Evaluación Cortes Semestrales'!$W$5:$W$68="No cumple")))) -> 0 | H14: =IF($E$4="C1 - Diciembre",SUMPRODUCT(('Evaluación Cortes Semestrales'!$B$5:$B$68=D14)*('Evaluación Cortes Semestrales'!$I$5:$I$68="Pendiente")),IF($E$4="C2 - Abril",SUMPRODUCT(('Evaluación Cortes Semestrales'!$B$5:$B$68=D14)*('Evaluación Cortes Semestrales'!$P$5:$P$68="Pendiente")),SUMPRODUCT(('Evaluación Cortes Semestrales'!$B$5:$B$68=D14)*('Evaluación Cortes Semestrales'!$W$5:$W$68="Pendiente")))) -> 0 | J14: Cumple | K14: =B14 -> 3
A15: Indicadores "En riesgo" | B15: =IF($E$4="C1 - Diciembre",COUNTIF('Evaluación Cortes Semestrales'!$I$5:$I$68,"En riesgo"),IF($E$4="C2 - Abril",COUNTIF('Evaluación Cortes Semestrales'!$P$5:$P$68,"En riesgo"),COUNTIF('Evaluación Cortes Semestrales'!$W$5:$W$68,"En riesgo"))) -> 0 | D15: 2. Claustro Académico | E15: =IF($E$4="C1 - Diciembre",SUMPRODUCT(('Evaluación Cortes Semestrales'!$B$5:$B$68=D15)*('Evaluación Cortes Semestrales'!$I$5:$I$68="Cumple")),IF($E$4="C2 - Abril",SUMPRODUCT(('Evaluación Cortes Semestrales'!$B$5:$B$68=D15)*('Evaluación Cortes Semestrales'!$P$5:$P$68="Cumple")),SUMPRODUCT(('Evaluación Cortes Semestrales'!$B$5:$B$68=D15)*('Evaluación Cortes Semestrales'!$W$5:$W$68="Cumple")))) -> 1 | F15: =IF($E$4="C1 - Diciembre",SUMPRODUCT(('Evaluación Cortes Semestrales'!$B$5:$B$68=D15)*('Evaluación Cortes Semestrales'!$I$5:$I$68="En riesgo")),IF($E$4="C2 - Abril",SUMPRODUCT(('Evaluación Cortes Semestrales'!$B$5:$B$68=D15)*('Evaluación Cortes Semestrales'!$P$5:$P$68="En riesgo")),SUMPRODUCT(('Evaluación Cortes Semestrales'!$B$5:$B$68=D15)*('Evaluación Cortes Semestrales'!$W$5:$W$68="En riesgo")))) -> 0 | G15: =IF($E$4="C1 - Diciembre",SUMPRODUCT(('Evaluación Cortes Semestrales'!$B$5:$B$68=D15)*('Evaluación Cortes Semestrales'!$I$5:$I$68="No cumple")),IF($E$4="C2 - Abril",SUMPRODUCT(('Evaluación Cortes Semestrales'!$B$5:$B$68=D15)*('Evaluación Cortes Semestrales'!$P$5:$P$68="No cumple")),SUMPRODUCT(('Evaluación Cortes Semestrales'!$B$5:$B$68=D15)*('Evaluación Cortes Semestrales'!$W$5:$W$68="No cumple")))) -> 0 | H15: =IF($E$4="C1 - Diciembre",SUMPRODUCT(('Evaluación Cortes Semestrales'!$B$5:$B$68=D15)*('Evaluación Cortes Semestrales'!$I$5:$I$68="Pendiente")),IF($E$4="C2 - Abril",SUMPRODUCT(('Evaluación Cortes Semestrales'!$B$5:$B$68=D15)*('Evaluación Cortes Semestrales'!$P$5:$P$68="Pendiente")),SUMPRODUCT(('Evaluación Cortes Semestrales'!$B$5:$B$68=D15)*('Evaluación Cortes Semestrales'!$W$5:$W$68="Pendiente")))) -> 0 | J15: En riesgo | K15: =B15 -> 0
A16: Indicadores "No cumple" | B16: =IF($E$4="C1 - Diciembre",COUNTIF('Evaluación Cortes Semestrales'!$I$5:$I$68,"No cumple"),IF($E$4="C2 - Abril",COUNTIF('Evaluación Cortes Semestrales'!$P$5:$P$68,"No cumple"),COUNTIF('Evaluación Cortes Semestrales'!$W$5:$W$68,"No cumple"))) -> 1 | D16: 3. Capital Humano (Administrativo) | E16: =IF($E$4="C1 - Diciembre",SUMPRODUCT(('Evaluación Cortes Semestrales'!$B$5:$B$68=D16)*('Evaluación Cortes Semestrales'!$I$5:$I$68="Cumple")),IF($E$4="C2 - Abril",SUMPRODUCT(('Evaluación Cortes Semestrales'!$B$5:$B$68=D16)*('Evaluación Cortes Semestrales'!$P$5:$P$68="Cumple")),SUMPRODUCT(('Evaluación Cortes Semestrales'!$B$5:$B$68=D16)*('Evaluación Cortes Semestrales'!$W$5:$W$68="Cumple")))) -> 0 | F16: =IF($E$4="C1 - Diciembre",SUMPRODUCT(('Evaluación Cortes Semestrales'!$B$5:$B$68=D16)*('Evaluación Cortes Semestrales'!$I$5:$I$68="En riesgo")),IF($E$4="C2 - Abril",SUMPRODUCT(('Evaluación Cortes Semestrales'!$B$5:$B$68=D16)*('Evaluación Cortes Semestrales'!$P$5:$P$68="En riesgo")),SUMPRODUCT(('Evaluación Cortes Semestrales'!$B$5:$B$68=D16)*('Evaluación Cortes Semestrales'!$W$5:$W$68="En riesgo")))) -> 0 | G16: =IF($E$4="C1 - Diciembre",SUMPRODUCT(('Evaluación Cortes Semestrales'!$B$5:$B$68=D16)*('Evaluación Cortes Semestrales'!$I$5:$I$68="No cumple")),IF($E$4="C2 - Abril",SUMPRODUCT(('Evaluación Cortes Semestrales'!$B$5:$B$68=D16)*('Evaluación Cortes Semestrales'!$P$5:$P$68="No cumple")),SUMPRODUCT(('Evaluación Cortes Semestrales'!$B$5:$B$68=D16)*('Evaluación Cortes Semestrales'!$W$5:$W$68="No cumple")))) -> 0 | H16: =IF($E$4="C1 - Diciembre",SUMPRODUCT(('Evaluación Cortes Semestrales'!$B$5:$B$68=D16)*('Evaluación Cortes Semestrales'!$I$5:$I$68="Pendiente")),IF($E$4="C2 - Abril",SUMPRODUCT(('Evaluación Cortes Semestrales'!$B$5:$B$68=D16)*('Evaluación Cortes Semestrales'!$P$5:$P$68="Pendiente")),SUMPRODUCT(('Evaluación Cortes Semestrales'!$B$5:$B$68=D16)*('Evaluación Cortes Semestrales'!$W$5:$W$68="Pendiente")))) -> 0 | J16: No cumple | K16: =B16 -> 1
A17: Indicadores "Pendiente" | B17: =IF($E$4="C1 - Diciembre",COUNTIF('Evaluación Cortes Semestrales'!$I$5:$I$68,"Pendiente"),IF($E$4="C2 - Abril",COUNTIF('Evaluación Cortes Semestrales'!$P$5:$P$68,"Pendiente"),COUNTIF('Evaluación Cortes Semestrales'!$W$5:$W$68,"Pendiente"))) -> 0 | D17: 4. Plataformas Tecnológicas | E17: =IF($E$4="C1 - Diciembre",SUMPRODUCT(('Evaluación Cortes Semestrales'!$B$5:$B$68=D17)*('Evaluación Cortes Semestrales'!$I$5:$I$68="Cumple")),IF($E$4="C2 - Abril",SUMPRODUCT(('Evaluación Cortes Semestrales'!$B$5:$B$68=D17)*('Evaluación Cortes Semestrales'!$P$5:$P$68="Cumple")),SUMPRODUCT(('Evaluación Cortes Semestrales'!$B$5:$B$68=D17)*('Evaluación Cortes Semestrales'!$W$5:$W$68="Cumple")))) -> 2 | F17: =IF($E$4="C1 - Diciembre",SUMPRODUCT(('Evaluación Cortes Semestrales'!$B$5:$B$68=D17)*('Evaluación Cortes Semestrales'!$I$5:$I$68="En riesgo")),IF($E$4="C2 - Abril",SUMPRODUCT(('Evaluación Cortes Semestrales'!$B$5:$B$68=D17)*('Evaluación Cortes Semestrales'!$P$5:$P$68="En riesgo")),SUMPRODUCT(('Evaluación Cortes Semestrales'!$B$5:$B$68=D17)*('Evaluación Cortes Semestrales'!$W$5:$W$68="En riesgo")))) -> 0 | G17: =IF($E$4="C1 - Diciembre",SUMPRODUCT(('Evaluación Cortes Semestrales'!$B$5:$B$68=D17)*('Evaluación Cortes Semestrales'!$I$5:$I$68="No cumple")),IF($E$4="C2 - Abril",SUMPRODUCT(('Evaluación Cortes Semestrales'!$B$5:$B$68=D17)*('Evaluación Cortes Semestrales'!$P$5:$P$68="No cumple")),SUMPRODUCT(('Evaluación Cortes Semestrales'!$B$5:$B$68=D17)*('Evaluación Cortes Semestrales'!$W$5:$W$68="No cumple")))) -> 0 | H17: =IF($E$4="C1 - Diciembre",SUMPRODUCT(('Evaluación Cortes Semestrales'!$B$5:$B$68=D17)*('Evaluación Cortes Semestrales'!$I$5:$I$68="Pendiente")),IF($E$4="C2 - Abril",SUMPRODUCT(('Evaluación Cortes Semestrales'!$B$5:$B$68=D17)*('Evaluación Cortes Semestrales'!$P$5:$P$68="Pendiente")),SUMPRODUCT(('Evaluación Cortes Semestrales'!$B$5:$B$68=D17)*('Evaluación Cortes Semestrales'!$W$5:$W$68="Pendiente")))) -> 0 | J17: Pendiente | K17: =B17 -> 0
A18: Datos completos | B18: =IF($E$4="C1 - Diciembre",COUNTIF('Evaluación Cortes Semestrales'!$H$5:$H$68,"Completo"),IF($E$4="C2 - Abril",COUNTIF('Evaluación Cortes Semestrales'!$O$5:$O$68,"Completo"),COUNTIF('Evaluación Cortes Semestrales'!$V$5:$V$68,"Completo"))) -> 4 | D18: 5. Posicionamiento Global | E18: =IF($E$4="C1 - Diciembre",SUMPRODUCT(('Evaluación Cortes Semestrales'!$B$5:$B$68=D18)*('Evaluación Cortes Semestrales'!$I$5:$I$68="Cumple")),IF($E$4="C2 - Abril",SUMPRODUCT(('Evaluación Cortes Semestrales'!$B$5:$B$68=D18)*('Evaluación Cortes Semestrales'!$P$5:$P$68="Cumple")),SUMPRODUCT(('Evaluación Cortes Semestrales'!$B$5:$B$68=D18)*('Evaluación Cortes Semestrales'!$W$5:$W$68="Cumple")))) -> 0 | F18: =IF($E$4="C1 - Diciembre",SUMPRODUCT(('Evaluación Cortes Semestrales'!$B$5:$B$68=D18)*('Evaluación Cortes Semestrales'!$I$5:$I$68="En riesgo")),IF($E$4="C2 - Abril",SUMPRODUCT(('Evaluación Cortes Semestrales'!$B$5:$B$68=D18)*('Evaluación Cortes Semestrales'!$P$5:$P$68="En riesgo")),SUMPRODUCT(('Evaluación Cortes Semestrales'!$B$5:$B$68=D18)*('Evaluación Cortes Semestrales'!$W$5:$W$68="En riesgo")))) -> 0 | G18: =IF($E$4="C1 - Diciembre",SUMPRODUCT(('Evaluación Cortes Semestrales'!$B$5:$B$68=D18)*('Evaluación Cortes Semestrales'!$I$5:$I$68="No cumple")),IF($E$4="C2 - Abril",SUMPRODUCT(('Evaluación Cortes Semestrales'!$B$5:$B$68=D18)*('Evaluación Cortes Semestrales'!$P$5:$P$68="No cumple")),SUMPRODUCT(('Evaluación Cortes Semestrales'!$B$5:$B$68=D18)*('Evaluación Cortes Semestrales'!$W$5:$W$68="No cumple")))) -> 1 | H18: =IF($E$4="C1 - Diciembre",SUMPRODUCT(('Evaluación Cortes Semestrales'!$B$5:$B$68=D18)*('Evaluación Cortes Semestrales'!$I$5:$I$68="Pendiente")),IF($E$4="C2 - Abril",SUMPRODUCT(('Evaluación Cortes Semestrales'!$B$5:$B$68=D18)*('Evaluación Cortes Semestrales'!$P$5:$P$68="Pendiente")),SUMPRODUCT(('Evaluación Cortes Semestrales'!$B$5:$B$68=D18)*('Evaluación Cortes Semestrales'!$W$5:$W$68="Pendiente")))) -> 0
D19: 6. Cultura Universitaria | E19: =IF($E$4="C1 - Diciembre",SUMPRODUCT(('Evaluación Cortes Semestrales'!$B$5:$B$68=D19)*('Evaluación Cortes Semestrales'!$I$5:$I$68="Cumple")),IF($E$4="C2 - Abril",SUMPRODUCT(('Evaluación Cortes Semestrales'!$B$5:$B$68=D19)*('Evaluación Cortes Semestrales'!$P$5:$P$68="Cumple")),SUMPRODUCT(('Evaluación Cortes Semestrales'!$B$5:$B$68=D19)*('Evaluación Cortes Semestrales'!$W$5:$W$68="Cumple")))) -> 0 | F19: =IF($E$4="C1 - Diciembre",SUMPRODUCT(('Evaluación Cortes Semestrales'!$B$5:$B$68=D19)*('Evaluación Cortes Semestrales'!$I$5:$I$68="En riesgo")),IF($E$4="C2 - Abril",SUMPRODUCT(('Evaluación Cortes Semestrales'!$B$5:$B$68=D19)*('Evaluación Cortes Semestrales'!$P$5:$P$68="En riesgo")),SUMPRODUCT(('Evaluación Cortes Semestrales'!$B$5:$B$68=D19)*('Evaluación Cortes Semestrales'!$W$5:$W$68="En riesgo")))) -> 0 | G19: =IF($E$4="C1 - Diciembre",SUMPRODUCT(('Evaluación Cortes Semestrales'!$B$5:$B$68=D19)*('Evaluación Cortes Semestrales'!$I$5:$I$68="No cumple")),IF($E$4="C2 - Abril",SUMPRODUCT(('Evaluación Cortes Semestrales'!$B$5:$B$68=D19)*('Evaluación Cortes Semestrales'!$P$5:$P$68="No cumple")),SUMPRODUCT(('Evaluación Cortes Semestrales'!$B$5:$B$68=D19)*('Evaluación Cortes Semestrales'!$W$5:$W$68="No cumple")))) -> 0 | H19: =IF($E$4="C1 - Diciembre",SUMPRODUCT(('Evaluación Cortes Semestrales'!$B$5:$B$68=D19)*('Evaluación Cortes Semestrales'!$I$5:$I$68="Pendiente")),IF($E$4="C2 - Abril",SUMPRODUCT(('Evaluación Cortes Semestrales'!$B$5:$B$68=D19)*('Evaluación Cortes Semestrales'!$P$5:$P$68="Pendiente")),SUMPRODUCT(('Evaluación Cortes Semestrales'!$B$5:$B$68=D19)*('Evaluación Cortes Semestrales'!$W$5:$W$68="Pendiente")))) -> 0
D20: 7. Apoyo Económico | E20: =IF($E$4="C1 - Diciembre",SUMPRODUCT(('Evaluación Cortes Semestrales'!$B$5:$B$68=D20)*('Evaluación Cortes Semestrales'!$I$5:$I$68="Cumple")),IF($E$4="C2 - Abril",SUMPRODUCT(('Evaluación Cortes Semestrales'!$B$5:$B$68=D20)*('Evaluación Cortes Semestrales'!$P$5:$P$68="Cumple")),SUMPRODUCT(('Evaluación Cortes Semestrales'!$B$5:$B$68=D20)*('Evaluación Cortes Semestrales'!$W$5:$W$68="Cumple")))) -> 0 | F20: =IF($E$4="C1 - Diciembre",SUMPRODUCT(('Evaluación Cortes Semestrales'!$B$5:$B$68=D20)*('Evaluación Cortes Semestrales'!$I$5:$I$68="En riesgo")),IF($E$4="C2 - Abril",SUMPRODUCT(('Evaluación Cortes Semestrales'!$B$5:$B$68=D20)*('Evaluación Cortes Semestrales'!$P$5:$P$68="En riesgo")),SUMPRODUCT(('Evaluación Cortes Semestrales'!$B$5:$B$68=D20)*('Evaluación Cortes Semestrales'!$W$5:$W$68="En riesgo")))) -> 0 | G20: =IF($E$4="C1 - Diciembre",SUMPRODUCT(('Evaluación Cortes Semestrales'!$B$5:$B$68=D20)*('Evaluación Cortes Semestrales'!$I$5:$I$68="No cumple")),IF($E$4="C2 - Abril",SUMPRODUCT(('Evaluación Cortes Semestrales'!$B$5:$B$68=D20)*('Evaluación Cortes Semestrales'!$P$5:$P$68="No cumple")),SUMPRODUCT(('Evaluación Cortes Semestrales'!$B$5:$B$68=D20)*('Evaluación Cortes Semestrales'!$W$5:$W$68="No cumple")))) -> 0 | H20: =IF($E$4="C1 - Diciembre",SUMPRODUCT(('Evaluación Cortes Semestrales'!$B$5:$B$68=D20)*('Evaluación Cortes Semestrales'!$I$5:$I$68="Pendiente")),IF($E$4="C2 - Abril",SUMPRODUCT(('Evaluación Cortes Semestrales'!$B$5:$B$68=D20)*('Evaluación Cortes Semestrales'!$P$5:$P$68="Pendiente")),SUMPRODUCT(('Evaluación Cortes Semestrales'!$B$5:$B$68=D20)*('Evaluación Cortes Semestrales'!$W$5:$W$68="Pendiente")))) -> 0
J22: Inventario de indicadores por temporalidad
J24: Mensual | K24: 2
J25: Semestral | K25: 3
J26: Anual | K26: 59

Sheet Listas
A1: Juicio evaluativo | B1: Estado del dato | C1: Corte | D1: Semáforo | E1: Temporalidad | F1: Meses
A2: Cumple | B2: Completo | C2: C1 - Diciembre | D2: 🟢 | E2: Mensual | F2: Sep
A3: En riesgo | B3: Parcial | C3: C2 - Abril | D3: 🟡 | E3: Semestral | F3: Oct
A4: No cumple | B4: En levantamiento | C4: C3 - Agosto | D4: 🔴 | E4: Anual | F4: Nov
A5: Pendiente | B5: No recibido | D5: ⚪ | F5: Dic
F6: Ene
F7: Feb
F8: Mar
F9: Abr
F10: May
F11: Jun
F12: Jul
F13: Ago

Sheet Instrucciones
A1: Dashboard de Evaluación del Plan de Efectividad Institucional 2025-2026
A3: Cómo usar este archivo
A5: 1. Revisa la hoja 'Calendario_Cortes' para seguir el ciclo académico de BGU: 01/09 al 31/08.
A7: 2. Usa la hoja 'Indicadores_Master' como referencia oficial del cuadro de dimensiones, metas, fórmula y responsable.
A9: 3. Registra datos recibidos de las divisiones en 'Registro_Datos'. Puedes cargar cada dato mensual, semestral o anual conforme llegue.
A11: 4. En la hoja 'Evaluación_3_Cortes' realiza el análisis formal del plan tres veces al año: C1-Diciembre, C2-Abril y C3-Agosto.
A13: 5. Para cada corte, consigna: valor reportado, estado del dato, juicio evaluativo, análisis, decisión/acción, responsable y fecha compromiso.
A15: 6. El dashboard resume automáticamente el avance del corte seleccionado y te ayuda a presentar resultados con semáforo institucional.
A17: 7. Indicadores anuales: en C1 y C2 puedes marcar 'Pendiente' o 'En levantamiento'; la evaluación final se consolida en C3-Ago.
A21: Criterio sugerido de evaluación
A23: Temporalidad | B23: Qué registrar | C23: Qué analizar en los cortes
A24: Mensual | B24: Dato de cada mes | C24: Analiza tendencia acumulada en C1, C2 y C3
A25: Semestral | B25: Dato al cierre de cada semestre | C25: En C1 usa avance preliminar si aplica; en C2 y C3 incorpora cierres semestrales
A26: Anual | B26: Dato una vez por año | C26: En C1/C2 deja evidencia del levantamiento; en C3 emite juicio final

Sheet Calendario Cortes
A1: Calendario de seguimiento y evaluación — BGU
A3: Ciclo académico | B3: 01 de septiembre al 31 de agosto
A6: Seguimiento | B6: Sep | C6: Oct | D6: Nov | E6: Dic | F6: Ene | G6: Feb | H6: Mar | I6: Abr | J6: May | K6: Jun | L6: Jul | M6: Ago
A7: Recepción de datos mensuales | B7: ● | C7: ● | D7: ● | E7: ● | F7: ● | G7: ● | H7: ● | I7: ● | J7: ● | K7: ● | L7: ● | M7: ●
A8: Recepción de datos semestrales | E8: avance | G8: cierre S1 | M8: cierre S2
A9: Levantamiento de anuales | B9: inicio | C9: ● | D9: ● | E9: ● | F9: ● | G9: ● | H9: ● | I9: ● | J9: ● | K9: ● | L9: ● | M9: cierre
A10: C1 - Evaluación institucional | E10: X
A11: C2 - Evaluación institucional | I11: X
A12: C3 - Evaluación institucional | M12: X
A15: Lectura recomendada por corte
A17: Corte | B17: Ventana de análisis recomendada | C17: Qué debe quedar documentado
A18: C1 - Diciembre | B18: Sep–Dic | C18: avance inicial, desvíos tempranos, acciones de corrección
A19: C2 - Abril | B19: Sep–Abr | C19: tendencia acumulada, primer cierre fuerte, seguimiento de acciones
A20: C3 - Agosto | B20: Sep–Ago | C20: cierre anual, cumplimiento final y lecciones para el siguiente ciclo

Sheet Registro Nuevo - Reporte 2025 -
A1: PLAN DE EFECTIVIDAD 2025 - 2026 EVALUACIÓN DE RESULTADOS 01 de septiembre del 2025 - 31 de agosto del 2026
A3: Estrategia | B3: Objetivo Institucional | C3: N° | D3: Código | E3: Nivel | F3: KPI y alcance | G3: Fórmula | H3: Meta | I3: Tipo de medida | J3: Fuente | K3: Reponsable | L3: Responsable ERP | M3: Frecuencia | N3: Resultados | O3: Evidencia | P3: Brecha | Q3: Estado | S3: Decision
A4: E1. Portafolio Académico | B4: Establecer una comunidad de aprendizaje diversa y global mediante una oferta autorizada, activa, pertinente y sostenible. | C4: 1 | D4: E1-I01 | E4: Intitucional | F4: Oferta efectiva de programas: Proporcion de programas autorizados que se encuentran activos, admiten estudiantes y cuentan con capacidad academica y operativa | G4: Programas activos / programas autorizados x 100 | H4: >=59% | I4: Cuantitativa directa | J4: Plan académico anual; catalogo; registro de programas | K4: Division of Academic Affairs / Division of Admissions and Marketing | L4: Ronald | M4: Semestral | N4: =11/11 -> 1 | O4: Catálogo BGU 12499Approved Data (1).pdf | Q4: Cumplido | R4: TRUE
C5: 2 | D5: E1-I02 | E5: Intitucional | F5: Retention Rate estudiantil: Persistencia de estudiantes elegibles de un periodo al siguiente; debe calcularse por cohorte, nivel y programa. | G5: Dashboard CIE | H5: >=85% | I5: Cuantitativa directa | J5: SIS/SMS; registros del Registrar | K5: Registrar / Division of Student Services | L5: Marisol | M5: Anual | N5: 0.91 | O5: Ratios 801 Data Collection (18.11.25) .xlsx | Q5: Cumplido | R5: TRUE | T5: Estado | U5: Criterio general | V5: Tratamiento | W5: Resultados
C6: 3 | D6: E1-I03 | E6: Intitucional | F6: Graduation Rate: Graduacion dentro de la ventana institucional de reporte, desagregada por nivel y cohorte madura. | G6: Graduados de la cohorte / estudiantes de la cohorte ajustada x 100 | H6: >=70% | I6: Cuantitativa directa | J6: Registros academicos; expedientes de graduación | K6: Registrar / Division of Student Services | L6: Ronald | M6: Anual | N6: 0.56 | O6: Copia de RATIOS DEAC - 24-03-26 Ratios 801 Data Collection (18.11.25) .xlsx | Q6: Parcialmente Cumplido | R6: TRUE | T6: Cumplido | U6: Meta alcanzada o superada, considerando la dirección del KPI. | V6: Mantener, elevar meta o cerrar mejora. | W6: =COUNTIF($Q$4:$Q40,"Cumplido") -> 18
C7: 4 | D7: E1-S01 | E7: Estratégico | F7: Pertinencia curricular internacional: Alineacion de los programas con demanda, regulacion, recomendaciones de advisory councils y resultados de aprendizaje | G7: Promedio de rubrica institucional de pertinencia (1-5) | H7: >=4/5 | I7: Mixta directa e indirecta | J7: Informes de revisión curricular; actas de advisory councils | K7: Division of Academic Affairs | L7: Ronald | M7: Anual | N7: 4.61 | O7: INFORME DE REVISIÓN CURRICULAR DEL PROGRAMA DE.docx | Q7: Cumplido | R7: TRUE | T7: Parcialmente cumplido | U7: Resultado mayor a 0 | V7: Analizar causa y fortalecer acciones. | W7: =COUNTIF($Q$4:$Q40,"Parcialmente cumplido") -> 5
C8: 5 | D8: E1-S02 | E8: Estratégico | F8: Diversidad geografica del alumnado: Cobertura internacional real de la matricula activa | G8: Conteo distinto de países de residencia de estudiantes activos | H8: >=20 países | I8: Cuantitativa directa | J8: Registro de admision; SIS/SMS | K8: Division of Admissions and Marketing / Registrar | L8: Antony Huaynapata | M8: Semestral | N8: 21 | O8: Paises/Registros | P8: 0 | Q8: Cumplido | R8: TRUE | T8: No cumplido | U8: Resultado igual a 0 | V8: Accion de mejora obligatoria cuando proceda. | W8: =COUNTIF($Q$4:$Q40,"No cumplido") -> 11
C9: 6 | D9: E1-O01 | E9: Operativo | F9: Programas autorizados por CIE: Cumplimiento regulatorio del portafolio autorizado. | G9: Conteo oficial a la fecha de corte | H9: >=11 | I9: Cuantitativa directa | J9: Registro público CIE; resoluciones y expedientes | K9: Division of Academic Affairs | L9: Ronald | M9: Anual | N9: 11 | O9: 12499Approved Data (1).pdf | Q9: Cumplido | R9: TRUE | T9: Sin datos | U9: La fuente no produjo informacion valida. | V9: Plan de obtencion y responsable; no registrar cero. | W9: =COUNTIF($Q$4:$Q40,"Sin datos") -> 0
A10: E2. Claustro Académico | B10: Mantener un claustro académico de calidad, suficiente, internacional, evaluado y en desarrollo continuo. | C10: 1 | D10: E2-I01 | E10: Institucional | F10: Evaluacion docente por estudiantes: Valoracion consolidada del desempeno docente en los cursos impartidos. | G10: Suma de puntuaciones validas / número de respuestas validas | H10: >=4/5 | I10: Cuantitativa indirecta | J10: Encuestas finales de curso | K10: Division of Academic Affairs / Division of Student Services | L10: Ronald | M10: Cada termino | N10: 4.54 | O10: Indicadores de Programas de Estudio BGU 2025–2026.pdf | Q10: Cumplido | R10: TRUE | T10: No aplicable / cohorte no madura | U10: El indicador no puede medirse legitimamente en el periodo. | V10: Justificar y programar la primera medición valida. | W10: =COUNTIF($Q$4:$Q40,"No aplicable / cohorte no madura") -> 0
C11: 2 | D11: E2-S01 | E11: Estratégico | F11: Actualizacion pedagogica: Participacion del faculty activo en el plan anual de desarrollo docente. | G11: Faculty que completa el plan / faculty activo x 100 | H11: >=70% | I11: Cuantitativa directa | J11: Registros de capacitación | K11: Division of Continuing Education / Division of Academic Affairs | L11: Ronald | M11: Anual | N11: 1 | O11: Registros de capacitación PLAN ANUAL DE DESARROLLO DOCENTE 2025 - 2026 INFORME DE CUMPLIMIENTO DEL PLAN ANUAL DE DESARROLLO DOCENTE 2025 - 2026 | Q11: Cumplido | R11: TRUE
C12: 3 | D12: E2-S02 | E12: Estratégico | F12: Permanencia docente: Continuidad del faculty elegible de un periodo academico al siguiente. | G12: Faculty que continua / faculty elegible inicial x 100 | H12: >=85% | I12: Cuantitativa directa | J12: Roster docente; contratos; nómina | K12: Division of Academic Affairs / Administration Services and Finance | L12: Ronald | M12: Anual | N12: =42/45 -> 0.93333333 | O12: Permanencia docente: 2025-2026 45 docentes y del 2026- 2027 tenemos 68 de ellos 42 de los 45 continuan | Q12: Cumplido | R12: TRUE | T12: Portafolio Académico | Y12: =IFERROR(__xludf.DUMMYFUNCTION("SPARKLINE(COUNTIF($Q$4:$Q$9,""Sin datos""),{""charttype"",""bar"";""max"",6;""color1"",""#9AA0A6""})"),"")
C13: 4 | D13: E2-O01 | E13: Operativo | F13: Diversidad internacional del claustro: Representacion de nacionalidades y experiencias academicas internacionales en el faculty activo. | G13: Conteo distinto de nacionalidades representadas | H13: >=10 países | I13: Cuantitativa directa | J13: Roster y expedientes de faculty | K13: Division of Academic Affairs | L13: Ronald | M13: Anual | N13: 11 paises | O13: Diversidad internacional del claustro | Q13: Cumplido | R13: TRUE | T13: Claustro Académico
C14: 5 | D14: E2-O02 | E14: Operativo | F14: Profesores Top en actividad: Proporcion de faculty que cumple la definicion institucional vigente y presta servicio academico efectivo en el periodo. | G14: Faculty Top activo / faculty activo x 100 | H14: >=10% | I14: Cuantitativa directa | J14: Expedientes y asignaciones docentes | K14: Division of Academic Affairs | L14: Ronald | M14: Anual | N14: =28/68 -> 0.41176471 | O14: Profesores Top en actividad 28 de 68 docentes | Q14: Cumplido | R14: TRUE | T14: Capital Humano Administrativo
A15: E3. Capital humano administrativo | B15: Contar con personal administrativo competente, estable y orientado a la eficiencia y al servicio. | C15: 1 | D15: E3-I01 | E15: Institucional | F15: Satisfaccion con servicios administrativos: Valoracion global de los servicios administrativos y de apoyo recibidos por los estudiantes | G15: Respuestas favorables / respuestas validas x 10 | H15: >=80% | I15: Cuantitativa indirecta | J15: Encuesta anual de satisfaccion; reporte de servicio | K15: Division of Administration Services and Finance / Division of Student Services | L15: Marisol | M15: Anual | N15: 0.92 | O15: Base Encuesta (8) ¿Qué tan satisfecho/a está con la atención y respuesta del área de soporte o servicios estudiantiles? 112 Encuestados al 14-07 neutral 19 satisfecho 38 muy satisfecho 46 | Q15: Cumplido | R15: TRUE | T15: Plataformas Tecnológicas
C16: 2 | D16: E3-I02 | E16: Institucional | F16: Clima laboral administrativo: Percepcion del staff sobre liderazgo, colaboración, recursos, desarrollo y ambiente laboral. | G16: Respuestas favorables / respuestas validas x 100 | H16: >=85% | I16: Cuantitativa indirecta | J16: Encuesta anual al staff | K16: Division of Administration Services and Finance | L16: Yajayra | M16: Anual | N16: 0.9669 | O16: Informe: Informe del Indicador 3.4 - Clima Laboral Administrativo - Plan de Efectividad 2025-2026 Anual2025 (1).pdf Indice de Satisfaccion (%)=Número total de respuestas/Número de respuestas con valores 3, 4 y 5​×100 Encuesta: ENCUESTA DEL CLIMA LABORAL STAFF - BGU.pdf | Q16: Cumplido | R16: TRUE | T16: Posicionamiento Global
C17: 3 | D17: E3-S01 | E17: Estratégico | F17: Permanencia del personal administrativo: Continuidad del personal elegible durante el periodo. | G17: Staff que continua / staff elegible inicial x 100 | H17: >=85% | I17: Cuantitativa directa | J17: Nómina y registros de recursos humanos | K17: Division of Administration Services and Finance | L17: Yajayra | M17: Anual | N17: 0.77 | O17: Permanencia del Personal Administrativo: Cuadro de asignación de personal y Job Description BGU | Q17: Parcialmente Cumplido | R17: TRUE | T17: Cultura Universitaria
C18: 4 | D18: E3-S02 | E18: Estratégico | F18: Capacitacion administrativa: Cumplimiento del plan anual de capacitación del staff. | G18: Staff que completa capacitación / staff activo x 100 | H18: >=80% | I18: Cuantitativa directa | J18: Registros de capacitación y certificados | K18: Division of Administration Services and Finance | L18: Yajayra | M18: Anual | N18: 0.9333 | O18: Informe con corte a Junio 2026 - 93,33%: Informe del Indicado 3.6 - Capacitación Administrativa | Q18: Cumplido | R18: TRUE | T18: Apoyo Económico y Acceso
C19: 5 | D19: E3-O01 | E19: Operativo | F19: Resolucion en primer contacto: Casos resueltos sin escalamiento ni reapertura dentro del periodo de control. | G19: Casos resueltos en primer contacto / casos cerrados x 100 | H19: >=70% | I19: Cuantitativa directa | J19: Zoho Desk, Bitrix u otro sistema de tickets | K19: Division of Student Services | L19: Marisol | M19: Mensual | O19: Miércoles 22 | Q19: No cumplido | R19: FALSE
C20: 6 | D20: E3-O02 | E20: Operativo | F20: Tiempo medio de respuesta: Tiempo promedio transcurrido entre la recepcion de una solicitud y la primera respuesta util | G20: Suma de horas hasta primera respuesta / solicitudes atendidas | H20: <=6 horas | I20: Cuantitativa directa | J20: Sistema de tickets y reportes de SLA | K20: Division of Student Services | L20: Marisol | M20: Mensual | O20: Miércoles 22 | Q20: No cumplido | R20: FALSE
A21: E4. Plataformas Tecnológicas | B21: Proveer plataformas tecnológicas seguras, disponibles y adoptadas que mejoren aprendizaje y operaciones. | C21: 1 | D21: E4-I01 | E21: Institucional | F21: Satisfaccion general con plataformas LMS/SIS: Valoracion de usabilidad, fiabilidad y experiencia del entorno tecnologico. | G21: Promedio de encuesta institucional (1-5) | H21: >=4/5 | I21: Cuantitativa indirecta | J21: Encuestas institucionales | K21: Division of Student Services / Division of Academic Affairs | L21: Anthony Robles | M21: Anual | N21: 3.97 | O21: https://support.blackwell.university/tech-infrastructure-reports/ | Q21: No cumplido | R21: TRUE
C22: 2 | D22: E4-S01 | E22: Estratégico | F22: Disponibilidad de sistemas criticos (Uptime): Continuidad del servicio en LMS, SIS y otros sistemas definidos como criticos. | G22: Horas disponibles / horas programadas x 100 | H22: >=99.9% | I22: Cuantitativa directa | J22: Logs y reportes de infraestructura | K22: Administration Services and Finance / Technology | L22: Anthony Robles | M22: Mensual | N22: Campus LMS = 99,99% Activa = 99,99% | O22: https://support.blackwell.university/Uptime | Q22: Cumplido | R22: TRUE
C23: 3 | D23: E4-S02 | E23: Estratégico | F23: Seguridad percibida: Confianza de estudiantes y faculty en la proteccion de datos personales y academicos. | G23: Respuestas favorables / respuestas validas x 100 | H23: >=90% | I23: Cuantitativa indirecta | J23: Encuesta anual de tecnologia y privacidad | K23: Division of Student Services / Division of Academic Affairs | L23: Anthony Robles | M23: Anual | N23: 0 | O23: No disponemos de la encuesta. Propuesta: https://support.blackwell.university/it-security/ Políticas de protección de datos y seguridad https://docs.google.com/document/d/1aBR7ldYpulRs7XhVqGswRm3MEF1tLrntJ-Oad22f0jQ/edit?tab=t.0 https://docs.google.com/document/d/1RFrZQHdt4AwnFpWNjISEgZEEMaypGjVfMpqHYNIHxFY/edit?tab=t.0 | Q23: No cumplido | R23: TRUE
C24: 4 | D24: E4-O01 | E24: Operativo | F24: Optimizacion de procesos: Procesos institucionales automatizados o redisenados y puestos en produccion durante el periodo. | G24: Conteo de procesos implementados y validados | H24: >=5 nuevos por año | I24: Cuantitativa directa | J24: Registro de procesos; actas de aceptacion | K24: Administration Services and Finance / Technology | L24: Anthony Robles | M24: Anual | N24: 15 | O24: Formularios Admision Acreditación Proyecto Capstone Chatfuel Master / doctorado / Licenciatura Chatfuel DCE ORA IA BGU Trabajos finales Sesiones Eurocoach Sesiones Mentoring Activa Student / Admin Reporte de Consolidado de Deudas y Recaudación de la Empresa por fechas. Sincronización de alumnos y sus cursos en el Moodle Retiro del estudiante y suspension de acceso al Moodle Sincronizacion de califaciones del moodle a la base de datos Activa Creacion de cuotas del producto y cuenta de google workspace despues de procesar el pago inicial del alumno Envio de correos electronicos con plantillas automaticas segun produto/categoria/empresa | Q24: Cumplido | R24: TRUE
C25: 5 | D25: E4-O02 | E25: Operativo | F25: Adopcion y capacitacion en plataformas: Usuarios obligados que completan la capacitacion anual en EdTech y ciberseguridad. | G25: Usuarios capacitados / usuarios obligados x 100 | H25: >=90% | I25: Cuantitativa directa | J25: LMS de capacitación; certificados | K25: Division of Academic Affairs / Division of Continuing Education | L25: Anthony Robles | M25: Anual | N25: 0 | O25: 0% NUEVO KPI - Por implementar Se gestionará cronograma para la capacitación | Q25: No cumplido | R25: TRUE
A26: E5. Posicionamiento Global | B26: Crear alianzas y oportunidades globales con impacto académico, profesional y reputacional medible. | C26: 1 | D26: E5-I01 | E26: Institucional | F26: Placement Rate: Graduados elegibles que reportan empleo, mejora laboral, emprendimiento o continuidad academica dentro de la ventana definida. | G26: Graduados con resultado favorable / graduados elegibles localizados x 100 | H26: >=85% | I26: Mixta directa e indirecta | J26: Encuesta de egresados; verificacion de Career Service | K26: Division of Student Services | L26: Marisol | M26: Anual | N26: =46/172 -> 0.26744186 | O26: Ratios 801 Data Collection (18.11.25) .xlsx Fueron 46 respuestas Población 172 | Q26: Parcialmente Cumplido | R26: FALSE
C27: 2 | D27: E5-I02 | E27: Institucional | F27: Percepcion de marca global: Reconocimiento y asociacion favorable de BGU entre grupos de interes seleccionados. | G27: Respuestas favorables / respuestas validas x 100 | H27: >=60% | I27: Cuantitativa indirecta | J27: Encuestas a estudiantes, alumni y aliados | K27: Division of Admissions and Marketing | L27: Antony Huaynapata | M27: Anual | N27: 0 | O27: El indicador E5-I02 (Percepción de marca global) no ha sido ejecutado a la fecha debido a que aún no se cuenta con el instrumento de medición (encuesta de percepción de marca) diseñado y aplicado a los grupos de interés. En las encuestas aplicadas hasta el momento por las áreas de Registros (Encuesta de Satisfacción Estudiantil), Servicios al Estudiante (Encuesta de Seguimiento al Egresado - BGU 2025) y Marketing (Buyer Persona), no se ha considerado este ítem. Para su cálculo, se requiere elaborar dicho instrumento, definir los grupos de interés a encuestar y establecer la periodicidad de aplicación. | Q27: No cumplido | R27: TRUE
C28: 3 | D28: E5-S01 | E28: Estratégico | F28: Relevancia de alianzas: Impacto academico, profesional o reputacional de los convenios activos | G28: Promedio de rubrica institucional de impacto (1-5) | H28: >=4/5 | I28: Mixta directa e indirecta | J28: Informe anual de convenios y evidencias de actividad | K28: Division of Admissions and Marketing / Division of Academic Affairs | L28: Ronald | M28: Anual | N28: 4 | O28: RELEVANCIA DE ALIANZAS - RÚBRICA | Q28: Cumplido | R28: TRUE
C29: 4 | D29: E5-S02 | E29: Estratégico | F29: Estudiantes en movilidad o experiencia internacional: Participacion estudiantil en intercambio, movilidad virtual, proyectos o actividades internacionales verificadas | G29: Conteo de participantes unicos | H29: >=50 | I29: Cuantitativa directa | J29: Registro de movilidad y actividades internacionales | K29: Division of Student Services / Division of Academic Affairs | L29: Ronald | M29: Anual | N29: 3 | O29: Meet and Greet, Congresos, American experience -New Business Leaders for a New World: 3 | Q29: Parcialmente Cumplido | R29: TRUE
C30: 5 | D30: E5-O01 | E30: Operativo | F30: Convenios activos: Convenios vigentes | G30: Conteo de convenios activos y verificados | H30: >=20 | I30: Cuantitativa directa | J30: Registro de convenios; actas; productos y reportes | K30: Division of Admissions and Marketing | L30: Antony Huaynapata | M30: Anual | N30: 15 | O30: CONVENIOS ACTIVOS VERIFICADOS | P30: =20-N30 -> 5 | Q30: Parcialmente Cumplido | R30: TRUE
A31: E6. Cultura Universitaria | B31: Promover una cultura ética, inclusiva, diversa y con sentido de pertenencia. | C31: 1 | D31: E6-I01 | E31: Institucional | F31: Sentido de pertenencia: Percepcion de estudiantes, faculty y staff sobre identificacion, inclusion y vinculacion con la comunidad BGU. | G31: Respuestas favorables / respuestas validas x 100 | H31: >=85% | I31: Cuantitativa indirecta | J31: Encuesta institucional de cultura y pertenencia | K31: President / Division of Student Services | L31: Marisol | M31: Anual | N31: 0 | O31: Se recomienda incluir: ¿Qué tan identificado/a se siente con los valores y la comunidad de Blackwell Global University? | Q31: No cumplido | R31: TRUE
C32: 2 | D32: E6-S01 | E32: Estratégico | F32: Indice de valores eticos y transversales (IVET): Desarrollo percibido y evidenciado de fraternidad, etica, crecimiento, inclusion, diversidad, compromiso y excelencia. | G32: (Suma de puntuaciones promedio / número de valores) x 100 / 5 | H32: >=85% | I32: Mixta directa e indirecta | J32: Rubricas, encuestas y evidencias de actividades formativas | K32: Division of Academic Affairs / Compliance | L32: Marisol | M32: Anual | N32: 0 | O32: (11) ¿Qué sugerencia tendría para mejorar o fortalecer la misión, visión, valores u objetivos institucionales? Menciona los valores, pero es una pregunta abierta y no permite calcular el IVET. | Q32: No cumplido | R32: TRUE
C33: 3 | D33: E6-O01 | E33: Operativo | F33: Capacitacion anual en etica e inclusion: Cumplimiento de la formacion obligatoria en etica, inclusion, integridad academica y conducta institucional. | G33: Personas que completan / personas obligadas x 100 | H33: >=90% | I33: Cuantitativa directa | J33: Registros de capacitación y certificados | K33: Compliance / Division of Administration Services and Finance | L33: Yajayra | M33: Anual | N33: 0 | O33: No se realizaron capacitaciones en ética e inclusión. | Q33: No cumplido | R33: TRUE
A34: E7. Apoyo Económico y Acceso | B34: Brindar apoyo económico transparente y sostenible que favorezca acceso y persistencia. | C34: 1 | D34: E7-I01 | E34: Institucional | F34: Persistencia de beneficiarios de apoyo: Continuidad academica de estudiantes que reciben becas, subsidios u otra ayuda institucional. | G34: Beneficiarios que continuan / beneficiarios elegibles iniciales x 100 | H34: >=85% | I34: Cuantitativa directa | J34: SIS/SMS; registro de beneficiarios | K34: Division of Student Services / Administration Services and Finance | L34: Marisol | M34: Anual | N34: 0.91 | O34: Ratios 801 Data Collection (18.11.25) .xlsx | Q34: Cumplido | R34: TRUE
C35: 2 | D35: E7-S01 | E35: Estratégico | F35: Satisfaccion con el apoyo economico y el acceso: Valoracion de claridad, oportunidad, equidad y utilidad del proceso de ayuda. | G35: Respuestas favorables / respuestas validas x 100 | H35: >=85% | I35: Cuantitativa indirecta | J35: Encuesta a beneficiarios y solicitantes | K35: Division of Student Services / Administration Services and Finance | L35: Yajayra | M35: Anual | N35: 0 | O35: No se corrió encuesta de Satisfaccion con el apoyo economico y el acceso. | Q35: No cumplido | R35: TRUE
C36: 3 | D36: E7-O01 | E36: Operativo | F36: Fondos destinados a becas y subsidios: Valor total de ayuda reconocida durante el periodo, con metodologia financiera documentada. | G36: Suma validada de ayudas otorgadas; separar efectivo, descuento y exoneracion | H36: USD 3.6 M | I36: Cuantitativa directa | J36: Registros financieros y de ayuda estudiantil | K36: Division of Administration Services and Finance | L36: Yajayra | M36: Anual | N36: USD 3,90 M | O36: Reporte: Monto Total de GRANT Reporte Consolidado de Admisión: Reporte Consolidado de Admisión Blackwell Global University | Q36: Cumplido | R36: TRUE
C37: 4 | D37: E7-O0 | E37: Operativo | F37: Fondos recibidos de donantes: Recursos efectivamente recibidos de terceros para apoyar acceso, becas o iniciativas estudiantiles. | G37: Suma de ingresos recibidos y conciliados | H37: USD 0.2 M | I37: Cuantitativa directa | J37: Contabilidad; contratos y recibos de donacion | K37: Division of Administration Services and Finance / President | L37: Yajayra | M37: Anual | N37: USD 0 M | O37: No se han recibido recursos de donantes | Q37: No cumplido | R37: TRUE
F38: Total | G38: 34

Sheet Registro Datos - NO VALIDO
A1: PLAN DE EFECTIVIDAD VIGENTE 2025 - 2026 | C1: Plan de Efectividad Institucional de BGU Año Académico 2025-2026 (30.12.25)
A2: Código | B2: Dimensión | C2: Indicador | D2: Meta esperada | E2: Temporalidad | F2: División BGU | G2: RESULTADOS ALCANZADOS | H2: FUENTES DE VERIFICACIÓN | I2: COMENTARIOS RELEVANTES | J2: ACCIONES DE MEJORA IDENTIFICADAS
A3: 46023 | B3: Portafolio académico | C3: Pertinencia Curricular Internacional | D3: ≥4/5 | E3: Anual | F3: Division of Academic Affairs
A4: 46054 | B4: Portafolio académico | C4: Diversificación Lingüística | D4: ≥30% | E4: Anual | F4: Division of Academic Affairs
A5: 46082 | B5: Portafolio académico | C5: Innovación Curricular Percibida | D5: ≥4/5 | E5: Anual | F5: Division of Academic Affairs
A6: 46113 | B6: Portafolio académico | C6: Flexibilidad Académica | D6: ≥80% satisfechos | E6: Anual | F6: Division of Academic Affairs
A7: 46143 | B7: Portafolio académico | C7: Reputación Académica Externa | D7: ≥4/5 | E7: Anual | F7: Division of Academic Affairs
A8: 46174 | B8: Portafolio académico | C8: Nº Programas Autorizados (CIE) | D8: ≥11 | E8: Anual | F8: Division of Academic Affairs
A9: 46204 | B9: Portafolio académico | C9: Graduation Rate General | D9: ≥70% | E9: Anual | F9: Division of Student Services | G9: 0.1246 | H9: RATIOS 01/07/2025 to 30/06/2026
A10: 46235 | B10: Portafolio académico | C10: Retention Rate Estudiantil | D10: ≥85% | E10: Anual | F10: Division of Student Services | G10: 0.9112 | H10: RATIOS 01/07/2025 to 30/06/2026
A11: 46266 | B11: Portafolio académico | C11: Diversidad Geográfica | D11: ≥20 países | E11: Anual | F11: Division of Admissions/Marketing | G11: Reporte consolidado de admisión: https://docs.google.com/spreadsheets/d/1D3xU22BJJ-9-PmpUytOa9QaXz1SqTwSGFxc5l8YFYfw/edit?gid=1233620087#gid=1233620087 | H11: Registro de admisión
A12: 46296 | B12: Portafolio académico | C12: Oferta Efectiva de Programas | D12: ≥59% | E12: Anual | F12: Division of Admissions/Marketing | G12: https://proxy.blackwell.university/?url=https://web02.fldoe.org/CIE/SearchSchools/SchoolSearchDetail.aspx?schoolID=12499 | H12: Información de la Commission For Independent Education | I12: Todos los programas activos.
A13: 46055 | B13: Claustro Académico | C13: Actualización Pedagógica | D13: ≥70% | E13: Anual | F13: División de Educación Continua
A14: 46083 | B14: Claustro Académico | C14: Diversidad Internacional | D14: ≥10 países | E14: Anual | F14: Division of Academic Affairs
A15: 46114 | B15: Claustro Académico | C15: Innovación Didáctica | D15: ≥4/5 | E15: Anual | F15: Division of Academic Affairs
A16: 46144 | B16: Claustro Académico | C16: Reconocimiento Externo del Claustro | D16: ≥4/5 | E16: Anual | F16: Division of Academic Affairs
A17: 46175 | B17: Claustro Académico | C17: % Profesores Top en Actividad | D17: ≥10% | E17: Anual | F17: Division of Academic Affairs
A18: 46205 | B18: Claustro Académico | C18: Permanencia Docente | D18: ≥85% | E18: Anual | F18: Division of Academic Affairs
A19: 46236 | B19: Claustro Académico | C19: Producción Científica | D19: ≥2 | E19: Anual | F19: Division of Academic Affairs
A20: 46267 | B20: Claustro Académico | C20: Satisfacción Académica | D20: ≥80% satisfechos | E20: Anual | F20: Division of Student Services | G20: Pendiente | H20: ERP BGU | I20: Encuesta en aplicación
A21: 46297 | B21: Claustro Académico | C21: Graduation Rate Posgrado | D21: ≥70% | E21: Anual | F21: Division of Student Services | G21: 0.875 | H21: RATIOS 01/07/2025 to 30/06/2026
A22: 46025 | B22: Capital Humano (Administrativo) | C22: Satisfacción con Central de Atención | D22: ≥4/5 | E22: Anual | F22: Division of Student Services | G22: Pendiente | H22: ERP BGU | I22: Encuesta en aplicación
A23: 46056 | B23: Capital Humano (Administrativo) | C23: Innovación Administrativa | D23: ≥6 | E23: Anual | F23: Division of Administration Services and Finance | G23: Reporte-15: https://docs.google.com/spreadsheets/d/1bLeOhiiIGSdhKg4g2lTu5em_xjEiKNEbRTOZYACUr88/edit?gid=359438294#gid=359438294 | H23: Reporte ACP SGC Bitrix
A24: 46084 | B24: Capital Humano (Administrativo) | C24: Accesibilidad de Servicios | D24: ≥85% | E24: Anual | F24: Division of Administration Services and Finance | G24: Sí se tiene la herramienta, sin embargo, aún no se tienen resultados | H24: Encuesta anual de satisfacción estudiantil / Informe Servicio al Estudiante | I24: Pregunta 16: https://docs.google.com/document/d/1eYH7OC0sK7pUDE-0Dis7DxZhq9HZ1MJAJrtAWZuIggM/edit?tab=t.0
A25: 46115 | B25: Capital Humano (Administrativo) | C25: Clima Laboral Administrativo | D25: ≥85% | E25: Anual | F25: Division of Administration Services and Finance | G25: 96,69% Informe: https://drive.google.com/file/d/15N5BwJ16rYWiTDyLzCRv9q-1AkMQxCM5/view?usp=drive_link Encuesta: https://drive.google.com/file/d/1id6MP22lDL-oL7ut2DuyCblQVOa6L3c4/view?usp=drive_link | H25: Informe de Encuesta anual al staff
A26: 46145 | B26: Capital Humano (Administrativo) | C26: Imagen Institucional Administrativa | D26: ≥85% | E26: Anual | F26: Division of Administration Services and Finance | G26: Sí se tiene la herramienta, sin embargo, aún no se tienen resultados | H26: Encuesta anual de satisfacción estudiantil / Informe Servicio al Estudiante | I26: Pregunta 11, 13 y 16: https://docs.google.com/document/d/1eYH7OC0sK7pUDE-0Dis7DxZhq9HZ1MJAJrtAWZuIggM/edit?tab=t.0
A27: 46176 | B27: Capital Humano (Administrativo) | C27: Capacitación Administrativa | D27: ≥80% | E27: Anual | F27: Division of Administration Services and Finance | G27: Informe con corte a Junio 2026 - 90%: https://docs.google.com/document/d/1ZNoM3Axx9AGv8Mab3N0cNxaGwCUcmTT-tSdI1w5UzS0/edit?tab=t.0 | H27: Informe anual de la ejecución del Plan de Capacitación RRHH
A28: 46206 | B28: Capital Humano (Administrativo) | C28: Resolución en Primer Contacto | D28: ≥70% | E28: Anual | F28: Division of Administration Services and Finance | G28: Reporte Zoho Desk - 75%: https://drive.google.com/file/d/1IcrzjQ2kybNCy7FDUZrIirYl6sUf1ehy/view?usp=drive_link | H28: Reporte Zoho Desk
A29: 46237 | B29: Capital Humano (Administrativo) | C29: Tiempo Medio de Respuesta | D29: ≤6h | E29: Anual | F29: Division of Administration Services and Finance | G29: Reporte Zoho Desk - 2h 39m: https://drive.google.com/file/d/1bWqmY7uuv-dGqXW2yYjRyVcRxm2UHCgF/view?usp=drive_link | H29: Reporte Zoho Desk
A30: 46268 | B30: Capital Humano (Administrativo) | C30: Retention Rate Administrativo | D30: ≥85% | E30: Anual | F30: Division of Administration Services and Finance | G30: 90,38% Personal Administrativo: https://drive.google.com/file/d/1xbTlC_Ca29hOTgVhrDN56taBAZnvhheA/view?usp=drive_link | H30: Nómina | I30: =((104-10)/104) -> 0.90384615
A31: 46298 | B31: Capital Humano (Administrativo) | C31: Satisfacción con Servicios Administrativos | D31: ≥80% | E31: Anual | F31: Division of Administration Services and Finance | G31: Sí se tiene la herramienta, sin embargo, aún no se tienen resultados | H31: Encuesta anual de satisfacción estudiantil / Informe Servicio al Estudiante | I31: Pregunta 15: https://docs.google.com/document/d/1eYH7OC0sK7pUDE-0Dis7DxZhq9HZ1MJAJrtAWZuIggM/edit?tab=t.0
A32: 46026 | B32: Plataformas Tecnológicas | C32: Satisfacción General con Plataformas (LMS/SIS) | D32: ≥4/5 | E32: Anual | F32: Division of Student Services / Division of Academic Affairs | G32: Pendiente | H32: ERP BGU | I32: Encuesta en aplicación
A33: 46057 | B33: Plataformas Tecnológicas | C33: Seguridad Percibida | D33: ≥90% | E33: Anual | F33: Division of Student Services / Division of Academic Affairs | G33: -- | H33: -- | I33: No se aplicó encuesta
A34: 46085 | B34: Plataformas Tecnológicas | C34: Innovación Tecnológica Percibida | D34: ≥4/5 | E34: Anual | F34: Division of Student Services / Division of Academic Affairs | G34: -- | H34: -- | I34: No se aplicó encuesta
A35: 46146 | B35: Plataformas Tecnológicas | C35: Optimización de Procesos | D35: ≥5 nuevos/año | E35: Anual | F35: Division of Administration Services and Finance | H35: Informe TI
A36: 46177 | B36: Plataformas Tecnológicas | C36: Adopción y Capacitación en Plataformas | D36: ≥90% | E36: Anual | F36: Division of Academic Affairs / Division of Continuing Education
A37: 46027 | B37: Posicionamiento Global | C37: Relevancia de Alianzas | D37: ≥4/5 | E37: Anual | F37: Division of Admissions/Marketing | G37: Pregrado y Posgrado | I37: Contamos con 4 convenios activos de los cuales 1 ofrece impacto a nivel matrículas con un 73% de la participación en matriculas de pregrado.
A38: 46058 | B38: Posicionamiento Global | C38: Percepción de Marca Global | D38: ≥60% | E38: Anual | F38: Division of Admissions/Marketing | I38: En las encuestas que se han aplicado hasta el momento (registros, servicios al estudiante y marketing) no se ha considerado el item
A39: 46086 | B39: Posicionamiento Global | C39: Satisfacción de Socios | D39: ≥4/5 | E39: Anual | F39: Division of Student Services | G39: Pendiente | H39: ERP BGU | I39: Nueva Propuesta
A40: 46117 | B40: Posicionamiento Global | C40: Reconocimiento en Rankings | D40: Aparecer en un ranking | E40: Anual | F40: Division of Admissions/Marketing | I40: En el periodo Julio 2025 / Junio 2026, no estamos en ninguno y se está prospectando fuentes con RF para trabajarlas.
A41: 46178 | B41: Posicionamiento Global | C41: Nº Alianzas Firmadas | D41: ≥20 | E41: Anual | F41: Division of Admissions/Marketing | G41: DDI.PR.01.RG.01 Control de Suscripción de Convenios Nacionales e Internacionales Rev.00_2026 | I41: En progreso 9 Por firmar
A42: 46208 | B42: Posicionamiento Global | C42: Nº Estudiantes en Movilidad | D42: ≥50 | E42: Anual | F42: Division of Student Services | G42: 3 | H42: ERP BGU | I42: Solicitar cifra visible de Intercambio por convenio
A43: 46300 | B43: Posicionamiento Global | C43: Membresías Internacionales | D43: ≥6 | E43: Anual | F43: Division of Administration Services and Finance | H43: Informe Licenciamiento y Acreditación
A44: 46028 | B44: Cultura Universitaria | C44: Índice de Formación Integral | D44: ≥4/5 | E44: Anual | F44: Division of Student Services | G44: -- | H44: -- | I44: No se aplicó encuesta
A45: 46059 | B45: Cultura Universitaria | C45: Inclusión y Diversidad Percibida | D45: ≥85% | E45: Anual | F45: Division of Student Services | G45: Pendiente | H45: ERP BGU | I45: Encuesta en aplicación | J45: Mejorar el planteamiento de la pregunta
A46: 46087 | B46: Cultura Universitaria | C46: Participación en Actividades Culturales | D46: ≥4/5 | E46: Anual | F46: Division of Student Services | G46: 0
A47: 46118 | B47: Cultura Universitaria | C47: Clima Ético Universitario | D47: ≥90% | E47: Anual | F47: Division of Student Services | G47: -- | I47: No se aplicó encuesta
A48: 46148 | B48: Cultura Universitaria | C48: Sentido de Pertenencia | D48: ≥85% | E48: Anual | F48: Division of Student Services | G48: -- | I48: No se aplicó encuesta
A49: 46179 | B49: Cultura Universitaria | C49: Participación en Cultura BGU | D49: ≥30% | E49: Anual | F49: Division of Student Services | G49: 2 | H49: Meet&Greet
A50: 46209 | B50: Cultura Universitaria | C50: Nº Actividades Inclusión y Diversidad | D50: ≥4 | E50: Anual | F50: Division of Student Services | G50: 1 | H50: https://es.linkedin.com/posts/blackwell-global-university_blackwell-global-university-presente-activity-7469856343982649344-1zXq | I50: BGU formó parte del proyecto internacional New Business Leaders for the New World (NBL2), desarrollado en Polonia y organizado por la Warsaw School of Economics (SGH). | J50: Identificar nuevos proyectos
A51: 46240 | B51: Cultura Universitaria | C51: Voluntariado Estudiantil | D51: ≥50 | E51: Anual | F51: Division of Student Services | G51: -- | I51: No se ejecutó
A52: 46271 | B52: Cultura Universitaria | C52: Student Satisfaction Rate (Cultura) | D52: ≥80% | E52: Anual | F52: Division of Student Services | G52: Pendiente | I52: 16.Blackwell Global University es cálida, amigable y brinda apoyo a los estudiantes.
A53: 46029 | B53: Apoyo Económico | C53: Satisfacción con Becas y Apoyo Económico | D53: Opinión favorable | E53: Anual | F53: Division of Student Services | G53: -- | I53: No se aplicó encuesta
A54: 46060 | B54: Apoyo Económico | C54: Percepción de Equidad | D54: Opinión favorable | E54: Anual | F54: Division of Student Services | G54: -- | I54: No se aplicó encuesta
A55: 46088 | B55: Apoyo Económico | C55: Impacto Percibido | D55: Opinión favorable | E55: Anual | F55: Division of Student Services | G55: -- | I55: No se aplicó encuesta
A56: 46149 | B56: Apoyo Económico | C56: Confianza en el Sistema de Becas | D56: Opinión favorable | E56: Anual | F56: Division of Student Services | G56: -- | I56: No se aplicó encuesta
A57: 46180 | B57: Apoyo Económico | C57: Monto Total de Becas | D57: ≥3.6M USD | E57: Anual | F57: Division of Administration Services and Finance | G57: 3,25 M Reporte: https://docs.google.com/spreadsheets/d/1DO8PuDas2OPdtnPAeii96zm_4h5Y1EgL4TFvRVCwZPo/edit?gid=0#gid=0 | H57: Informe Finanzas
A58: 46210 | B58: Apoyo Económico | C58: Fondos Captados de Donantes | D58: ≥0.2M USD | E58: Anual | F58: Division of Administration Services and Finance | G58: 0 | H58: Informe Finanzas
A59: 46241 | B59: Apoyo Económico | C59: % Estudiantes con Apoyo Económico | D59: ≥25% | E59: Anual | F59: Division of Administration Services and Finance | G59: 1 | H59: Registros becas
A60: 46272 | B60: Apoyo Económico | C60: Retention Rate Becados | D60: ≥85% | E60: Anual | F60: Division of Student Services | G60: Pendiente
A61: 46302 | B61: Apoyo Económico | C61: Graduation Rate Becados | D61: ≥70% | E61: Anual | F61: Division of Student Services | G61: Pendiente

Sheet Registro Datos - Reportes semes
A1: Fecha de recepción | B1: Año académico | C1: Mes / periodo | D1: Corte asociado | E1: Código | F1: Indicador | G1: Dimensión | H1: Temporalidad | I1: División BGU | J1: Valor reportado | K1: Unidad / escala | L1: Fuente / evidencia | M1: Link / ubicación | N1: Observaciones
A2: Septiembre / Octubre 2025 | B2: 2025 - 2026 | C2: Fall | D2: Septiembre - Diciembre | E2: 46116 | F2: Disponibilidad de Sistemas Críticos (Uptime) | G2: Plataformas Tecnológicas | H2: Mensual | I2: Division of Administration Services and Finance | J2: LMS 99,99% / SIS 99.95% | K2: % | L2: Reporte de indicador mensual | M2: correo | N2: CUMPLE
A3: 45962 | B3: 2025 - 2026 | C3: Fall | D3: Septiembre - Diciembre | E3: 46116 | F3: Disponibilidad de Sistemas Críticos (Uptime) | G3: Plataformas Tecnológicas | H3: Mensual | I3: Division of Administration Services and Finance | J3: LMS 99,99% / SIS 99.94% | K3: % | L3: Reporte de indicador mensual | M3: correo | N3: CUMPLE
A4: 45992 | B4: 2025 - 2026 | C4: Fall | D4: Septiembre - Diciembre | E4: 46116 | F4: Disponibilidad de Sistemas Críticos (Uptime) | G4: Plataformas Tecnológicas | H4: Mensual | I4: Division of Administration Services and Finance | J4: LMS 99,99% / SIS 99.97% | K4: % | L4: Reporte de indicador mensual | M4: correo | N4: CUMPLE
A5: 46023 | B5: 2025 - 2026 | C5: Spring | D5: Enero - Abril | E5: 46116 | F5: Disponibilidad de Sistemas Críticos (Uptime) | G5: Plataformas Tecnológicas | H5: Mensual | I5: Division of Administration Services and Finance | J5: LMS 99,98% / SIS 99.95% | K5: % | L5: Reporte de indicador mensual | M5: correo | N5: CUMPLE
A6: 46054 | B6: 2025 - 2026 | C6: Spring | D6: Enero - Abril | E6: 46116 | F6: Disponibilidad de Sistemas Críticos (Uptime) | G6: Plataformas Tecnológicas | H6: Mensual | I6: Division of Administration Services and Finance | J6: LMS 99,98% / SIS 99.96% | K6: % | L6: Reporte de indicador mensual | M6: correo | N6: CUMPLE
A7: 46082 | B7: 2025 - 2026 | C7: Spring | D7: Enero - Abril | E7: 46116 | F7: Disponibilidad de Sistemas Críticos (Uptime) | G7: Plataformas Tecnológicas | H7: Mensual | I7: Division of Administration Services and Finance | J7: LMS 100% / SIS 100% | K7: % | L7: Reporte de indicador mensual | M7: correo | N7: CUMPLE
A8: - | B8: 2025 - 2026 | C8: Spring | D8: Enero - Abril | E8: 46116 | F8: Disponibilidad de Sistemas Críticos (Uptime) | G8: Plataformas Tecnológicas | H8: Mensual | I8: Division of Administration Services and Finance | J8: LMS 100% / SIS 100% | K8: % | L8: Reporte de indicador mensual | M8: correo | N8: CUMPLE
A9: 46029 | B9: 2025 - 2026 | C9: Fall | D9: Septiembre - Diciembre | E9: 46207 | F9: Costo de Tecnología por Estudiante | G9: Posicionamiento Global | H9: Semestral | I9: Division of Administration Services and Finance | J9: 4.95 $ | K9: $ | L9: Reporte de tecnología por estudiante | M9: correo | N9: CUMPLE
A10: - | B10: 2025 - 2026 | C10: Spring | D10: Enero - Abril | E10: 46207 | F10: Costo de Tecnología por Estudiante | G10: Posicionamiento Global | H10: Semestral | I10: Division of Administration Services and Finance | J10: 9.80 USD | K10: $ | L10: Reporte de tecnología por estudiante | M10: correo | N10: CUMPLE
A11: 46029 | B11: 2025 - 2026 | C11: Fall | D11: Septiembre - Diciembre | E11: 46239 | F11: Placement Rate | G11: Posicionamiento Global | H11: Semestral | I11: Student Services Division | J11: 0.72 | K11: % | L11: Indicadores de desempeño | M11: correo | N11: NO CUMPLE LA META >85%
A12: - | B12: 2025 - 2026 | C12: Spring | D12: Enero - Abril | E12: 46239 | F12: Placement Rate | G12: Posicionamiento Global | H12: Semestral | I12: Student Services Division | J12: PENDIENTE | K12: - | L12: - | M12: - | N12: información obtenida en MAYO 2026
A13: 46023 | B13: 2025 - 2026 | C13: Fall | D13: Septiembre - Diciembre | E13: 46024 | F13: Evaluación Docente por Estudiantes | G13: Claustro Académico | H13: Mensual | I13: Student Services Division | J13: 5 | K13: - | L13: INDICADORES DE DESEMPEÑO IEP | M13: correo | N13: CUMPLE
A14: 46023 | B14: 2025 - 2026 | C14: Fall | D14: Septiembre - Diciembre | E14: 46024 | F14: Evaluación Docente por Estudiantes | G14: Claustro Académico | H14: Mensual | I14: Student Services Division | J14: 5 | K14: - | L14: INDICADORES DE DESEMPEÑO IEP | M14: correo | N14: CUMPLE
A15: 46023 | B15: 2025 - 2026 | C15: Fall | D15: Septiembre - Diciembre | E15: 46024 | F15: Evaluación Docente por Estudiantes | G15: Claustro Académico | H15: Mensual | I15: Student Services Division | J15: 5 | K15: - | L15: INDICADORES DE DESEMPEÑO IEP | M15: correo | N15: CUMPLE
A16: 46023 | B16: 2025 - 2026 | C16: Fall | D16: Septiembre - Diciembre | E16: 46024 | F16: Evaluación Docente por Estudiantes | G16: Claustro Académico | H16: Mensual | I16: Student Services Division | J16: 4 | K16: - | L16: INDICADORES DE DESEMPEÑO IEP | M16: correo | N16: CUMPLE
A17: - | B17: 2025 - 2026 | C17: Spring | D17: Enero - Abril | E17: 46024 | F17: Evaluación Docente por Estudiantes | G17: Claustro Académico | H17: Mensual | I17: Student Services Division | J17: 4 | K17: - | L17: INDICADORES DE DESEMPEÑO IEP | M17: correo | N17: CUMPLE
A18: - | B18: 2025 - 2026 | C18: Spring | D18: Enero - Abril | E18: 46024 | F18: Evaluación Docente por Estudiantes | G18: Claustro Académico | H18: Mensual | I18: Student Services Division | J18: 5 | K18: - | L18: INDICADORES DE DESEMPEÑO IEP | M18: correo | N18: CUMPLE
A19: - | B19: 2025 - 2026 | C19: Spring | D19: Enero - Abril | E19: 46024 | F19: Evaluación Docente por Estudiantes | G19: Claustro Académico | H19: Mensual | I19: Student Services Division | J19: 4.62 | K19: - | L19: INDICADORES DE DESEMPEÑO IEP | M19: correo | N19: CUMPLE
A20: - | B20: 2025 - 2026 | C20: Spring | D20: Enero - Abril | E20: 46024 | F20: Evaluación Docente por Estudiantes | G20: Claustro Académico | H20: Mensual | I20: Student Services Division | J20: - | K20: - | L20: - | M20: - | N20: información obtenida en MAYO 2026
A21: - | B21: 2025 - 2026 | C21: Fall | D21: Septiembre - Diciembre | E21: 46270 | F21: Participación de BGU en foros/seminarios internacionales | G21: Posicionamiento Global | H21: Semestral | I21: Academic Affairs Division | J21: - | K21: - | L21: - | M21: - | N21: No reportó
A22: - | B22: 2025 - 2026 | C22: Spring | D22: Enero - Abril | E22: 46270 | F22: Participación de BGU en foros/seminarios internacionales | G22: Posicionamiento Global | H22: Semestral | I22: Academic Affairs Division | J22: - | K22: - | L22: - | M22: - | N22: No reportó
A23: 46082 | B23: 2025 - 2026 | C23: Spring | D23: Enero - Abril | E23: 46266 | F23: Diversidad Geográfica | G23: Portafolio Académico | H23: Anual | I23: Admissions and Marketing Division | J23: 20 | K23: N° | L23: Plan de Efectividad Institucional de BGU Año Académico 2025-2026 (30.12.25) | M23: Drive | N23: Avance
A24: 46082 | B24: 2025 - 2026 | C24: Spring | D24: Enero - Abril | E24: 46296 | F24: Oferta Efectiva de Programas | G24: Portafolio Académico | H24: Anual | I24: Admissions and Marketing Division | J24: 1 | K24: % | L24: Plan de Efectividad Institucional de BGU Año Académico 2025-2026 (30.12.25) | M24: Drive | N24: Avance
A25: 46082 | B25: 2025 - 2026 | C25: Spring | D25: Enero - Abril | E25: 46027 | F25: Impacto académico de convenios | G25: Posicionamiento Global | H25: Anual | I25: Admissions and Marketing Division | J25: 46143 | K25: N° | L25: Pregrado y Posgrado | M25: Drive | N25: Avance
A26: 46082 | B26: 2025 - 2026 | C26: Spring | D26: Enero - Abril | E26: 46058 | F26: Opinión sobre visibilidad internacional Asociación de marca | G26: Posicionamiento Global | H26: Anual | I26: Admissions and Marketing Division | J26: en proceso | K26: - | L26: - | M26: - | N26: Avance
A27: 46082 | B27: 2025 - 2026 | C27: Spring | D27: Enero - Abril | E27: 46117 | F27: Posición en rankings | G27: Posicionamiento Global | H27: Anual | I27: Admissions and Marketing Division | J27: 0 | K27: - | L27: - | M27: - | N27: Avance
A28: 46082 | B28: 2025 - 2026 | C28: Spring | D28: Enero - Abril | E28: 46178 | F28: Cantidad de convenios activos | G28: Posicionamiento Global | H28: Anual | I28: Admissions and Marketing Division | J28: 4 | K28: N° | L28: DDI.PR.01.RG.01 Control de Suscripción de Convenios Nacionales e Internacionales Rev.00_2026 | M28: Drive | N28: Avance
A29: 46082 | B29: 2025 - 2026 | C29: Spring | D29: Enero - Abril | E29: 46115 | F29: Clima Laboral Administrativo | G29: Capital Humano | H29: Anual | I29: Division of Administration Services and Finance | J29: en proceso | K29: % | L29: Informe sobre la encuesta de Clima Laboral | M29: correo | N29: Avance
B31: 2025 - 2026 | C31: Summer | D31: Mayo | E31: 46024 | F31: Evaluación Docente por Estudiantes | G31: Claustro Académico | H31: Mensual | I31: Student Services Division | J31: Pendiente
B32: 2025 - 2026 | C32: Summer | D32: Junio | E32: 46024 | F32: Evaluación Docente por Estudiantes | G32: Claustro Académico | H32: Mensual | I32: Student Services Division | J32: Pendiente
B33: 2025 - 2026 | C33: Summer | D33: Julio | E33: 46024 | F33: Evaluación Docente por Estudiantes | G33: Claustro Académico | H33: Mensual | I33: Student Services Division | J33: Pendiente
B34: 2025 - 2026 | C34: Summer | D34: Agosto | E34: 46024 | F34: Evaluación Docente por Estudiantes | G34: Claustro Académico | H34: Mensual | I34: Student Services Division | J34: Pendiente
B35: 2025 - 2026 | C35: Summer | D35: Mayo | E35: 46116 | F35: Disponibilidad de Sistemas Críticos (Uptime) | G35: Plataformas Tecnológicas | H35: Mensual | I35: Division of Administration Services and Finance | J35: Pendiente
B36: 2025 - 2026 | C36: Summer | D36: Junio | E36: 46116 | F36: Disponibilidad de Sistemas Críticos (Uptime) | G36: Plataformas Tecnológicas | H36: Mensual | I36: Division of Administration Services and Finance | J36: Pendiente
B37: 2025 - 2026 | C37: Summer | D37: Julio | E37: 46116 | F37: Disponibilidad de Sistemas Críticos (Uptime) | G37: Plataformas Tecnológicas | H37: Mensual | I37: Division of Administration Services and Finance | J37: Pendiente
B38: 2025 - 2026 | C38: Summer | D38: Agosto | E38: 46116 | F38: Disponibilidad de Sistemas Críticos (Uptime) | G38: Plataformas Tecnológicas | H38: Mensual | I38: Division of Administration Services and Finance | J38: Pendiente
B39: 2025 - 2026 | C39: Summer | D39: Mayo - Julio | E39: 46207 | F39: Costo de Tecnología por Estudiante | G39: Posicionamiento Global | H39: Semestral | I39: Division of Administration Services and Finance | J39: Pendiente
B40: 2025 - 2026 | C40: Summer | D40: Mayo - Julio | E40: 46239 | F40: Placement Rate | G40: Posicionamiento Global | H40: Semestral | I40: Student Services Division | J40: Pendiente
F50: {=IFERROR(XLOOKUP(E50,'Indicadores Master'!$D$2:$D$65,'Indicadores Master'!$E$2:$E$65,""),"")} | G50: {=IFERROR(XLOOKUP(E50,'Indicadores Master'!$D$2:$D$65,'Indicadores Master'!$A$2:$A$65,""),"")}
F51: {=IFERROR(XLOOKUP(E51,'Indicadores Master'!$D$2:$D$65,'Indicadores Master'!$E$2:$E$65,""),"")} | G51: {=IFERROR(XLOOKUP(E51,'Indicadores Master'!$D$2:$D$65,'Indicadores Master'!$A$2:$A$65,""),"")}
F52: {=IFERROR(XLOOKUP(E52,'Indicadores Master'!$D$2:$D$65,'Indicadores Master'!$E$2:$E$65,""),"")} | G52: {=IFERROR(XLOOKUP(E52,'Indicadores Master'!$D$2:$D$65,'Indicadores Master'!$A$2:$A$65,""),"")} | H52: {=IFERROR(XLOOKUP(E52,'Indicadores Master'!$D$2:$D$65,'Indicadores Master'!$K$2:$K$65,""),"")} | I52: {=IFERROR(XLOOKUP(E52,'Indicadores Master'!$D$2:$D$65,'Indicadores Master'!$J$2:$J$65,""),"")}
F53: {=IFERROR(XLOOKUP(E53,'Indicadores Master'!$D$2:$D$65,'Indicadores Master'!$E$2:$E$65,""),"")} | G53: {=IFERROR(XLOOKUP(E53,'Indicadores Master'!$D$2:$D$65,'Indicadores Master'!$A$2:$A$65,""),"")} | H53: {=IFERROR(XLOOKUP(E53,'Indicadores Master'!$D$2:$D$65,'Indicadores Master'!$K$2:$K$65,""),"")} | I53: {=IFERROR(XLOOKUP(E53,'Indicadores Master'!$D$2:$D$65,'Indicadores Master'!$J$2:$J$65,""),"")}
F54: {=IFERROR(XLOOKUP(E54,'Indicadores Master'!$D$2:$D$65,'Indicadores Master'!$E$2:$E$65,""),"")} | G54: {=IFERROR(XLOOKUP(E54,'Indicadores Master'!$D$2:$D$65,'Indicadores Master'!$A$2:$A$65,""),"")} | H54: {=IFERROR(XLOOKUP(E54,'Indicadores Master'!$D$2:$D$65,'Indicadores Master'!$K$2:$K$65,""),"")} | I54: {=IFERROR(XLOOKUP(E54,'Indicadores Master'!$D$2:$D$65,'Indicadores Master'!$J$2:$J$65,""),"")}
F55: {=IFERROR(XLOOKUP(E55,'Indicadores Master'!$D$2:$D$65,'Indicadores Master'!$E$2:$E$65,""),"")} | G55: {=IFERROR(XLOOKUP(E55,'Indicadores Master'!$D$2:$D$65,'Indicadores Master'!$A$2:$A$65,""),"")} | H55: {=IFERROR(XLOOKUP(E55,'Indicadores Master'!$D$2:$D$65,'Indicadores Master'!$K$2:$K$65,""),"")} | I55: {=IFERROR(XLOOKUP(E55,'Indicadores Master'!$D$2:$D$65,'Indicadores Master'!$J$2:$J$65,""),"")}
F56: {=IFERROR(XLOOKUP(E56,'Indicadores Master'!$D$2:$D$65,'Indicadores Master'!$E$2:$E$65,""),"")} | G56: {=IFERROR(XLOOKUP(E56,'Indicadores Master'!$D$2:$D$65,'Indicadores Master'!$A$2:$A$65,""),"")} | H56: {=IFERROR(XLOOKUP(E56,'Indicadores Master'!$D$2:$D$65,'Indicadores Master'!$K$2:$K$65,""),"")} | I56: {=IFERROR(XLOOKUP(E56,'Indicadores Master'!$D$2:$D$65,'Indicadores Master'!$J$2:$J$65,""),"")}
F57: {=IFERROR(XLOOKUP(E57,'Indicadores Master'!$D$2:$D$65,'Indicadores Master'!$E$2:$E$65,""),"")} | G57: {=IFERROR(XLOOKUP(E57,'Indicadores Master'!$D$2:$D$65,'Indicadores Master'!$A$2:$A$65,""),"")} | H57: {=IFERROR(XLOOKUP(E57,'Indicadores Master'!$D$2:$D$65,'Indicadores Master'!$K$2:$K$65,""),"")} | I57: {=IFERROR(XLOOKUP(E57,'Indicadores Master'!$D$2:$D$65,'Indicadores Master'!$J$2:$J$65,""),"")}
F58: {=IFERROR(XLOOKUP(E58,'Indicadores Master'!$D$2:$D$65,'Indicadores Master'!$E$2:$E$65,""),"")} | G58: {=IFERROR(XLOOKUP(E58,'Indicadores Master'!$D$2:$D$65,'Indicadores Master'!$A$2:$A$65,""),"")} | H58: {=IFERROR(XLOOKUP(E58,'Indicadores Master'!$D$2:$D$65,'Indicadores Master'!$K$2:$K$65,""),"")} | I58: {=IFERROR(XLOOKUP(E58,'Indicadores Master'!$D$2:$D$65,'Indicadores Master'!$J$2:$J$65,""),"")}
F59: {=IFERROR(XLOOKUP(E59,'Indicadores Master'!$D$2:$D$65,'Indicadores Master'!$E$2:$E$65,""),"")} | G59: {=IFERROR(XLOOKUP(E59,'Indicadores Master'!$D$2:$D$65,'Indicadores Master'!$A$2:$A$65,""),"")} | H59: {=IFERROR(XLOOKUP(E59,'Indicadores Master'!$D$2:$D$65,'Indicadores Master'!$K$2:$K$65,""),"")} | I59: {=IFERROR(XLOOKUP(E59,'Indicadores Master'!$D$2:$D$65,'Indicadores Master'!$J$2:$J$65,""),"")}
F60: {=IFERROR(XLOOKUP(E60,'Indicadores Master'!$D$2:$D$65,'Indicadores Master'!$E$2:$E$65,""),"")} | G60: {=IFERROR(XLOOKUP(E60,'Indicadores Master'!$D$2:$D$65,'Indicadores Master'!$A$2:$A$65,""),"")} | H60: {=IFERROR(XLOOKUP(E60,'Indicadores Master'!$D$2:$D$65,'Indicadores Master'!$K$2:$K$65,""),"")} | I60: {=IFERROR(XLOOKUP(E60,'Indicadores Master'!$D$2:$D$65,'Indicadores Master'!$J$2:$J$65,""),"")}
F61: {=IFERROR(XLOOKUP(E61,'Indicadores Master'!$D$2:$D$65,'Indicadores Master'!$E$2:$E$65,""),"")} | G61: {=IFERROR(XLOOKUP(E61,'Indicadores Master'!$D$2:$D$65,'Indicadores Master'!$A$2:$A$65,""),"")} | H61: {=IFERROR(XLOOKUP(E61,'Indicadores Master'!$D$2:$D$65,'Indicadores Master'!$K$2:$K$65,""),"")} | I61: {=IFERROR(XLOOKUP(E61,'Indicadores Master'!$D$2:$D$65,'Indicadores Master'!$J$2:$J$65,""),"")}
F62: {=IFERROR(XLOOKUP(E62,'Indicadores Master'!$D$2:$D$65,'Indicadores Master'!$E$2:$E$65,""),"")} | G62: {=IFERROR(XLOOKUP(E62,'Indicadores Master'!$D$2:$D$65,'Indicadores Master'!$A$2:$A$65,""),"")} | H62: {=IFERROR(XLOOKUP(E62,'Indicadores Master'!$D$2:$D$65,'Indicadores Master'!$K$2:$K$65,""),"")} | I62: {=IFERROR(XLOOKUP(E62,'Indicadores Master'!$D$2:$D$65,'Indicadores Master'!$J$2:$J$65,""),"")}
F63: {=IFERROR(XLOOKUP(E63,'Indicadores Master'!$D$2:$D$65,'Indicadores Master'!$E$2:$E$65,""),"")} | G63: {=IFERROR(XLOOKUP(E63,'Indicadores Master'!$D$2:$D$65,'Indicadores Master'!$A$2:$A$65,""),"")} | H63: {=IFERROR(XLOOKUP(E63,'Indicadores Master'!$D$2:$D$65,'Indicadores Master'!$K$2:$K$65,""),"")} | I63: {=IFERROR(XLOOKUP(E63,'Indicadores Master'!$D$2:$D$65,'Indicadores Master'!$J$2:$J$65,""),"")}
... F213: {=IFERROR(XLOOKUP(E213,'Indicadores Master'!$D$2:$D$65,'Indicadores Master'!$E$2:$E$65,""),"")} | G213: {=IFERROR(XLOOKUP(E213,'Indicadores Master'!$D$2:$D$65,'Indicadores Master'!$A$2:$A$65,""),"")} | H213: {=IFERROR(XLOOKUP(E213,'Indicadores Master'!$D$2:$D$65,'Indicadores Master'!$K$2:$K$65,""),"")} | I213: {=IFERROR(XLOOKUP(E213,'Indicadores Master'!$D$2:$D$65,'Indicadores Master'!$J$2:$J$65,""),"")}

Sheet Evaluación Cortes Semestrales
A1: Matriz de análisis y evaluación formal del Plan de Efectividad
A3: Código | B3: Dimensión | C3: Indicador | D3: Temporalidad | E3: Meta esperada | F3: División BGU | G3: C1 - Diciembre | N3: C2 - Abril | U3: C3 - Agosto
G4: Valor del corte | H4: Estado del dato | I4: Juicio evaluativo | J4: Semáforo | K4: Análisis | L4: Acción / decisión | M4: Fecha compromiso | N4: Valor del corte | O4: Estado del dato | P4: Juicio evaluativo | Q4: Semáforo | R4: Análisis | S4: Acción / decisión | T4: Fecha compromiso | U4: Valor del corte | V4: Estado del dato | W4: Juicio evaluativo | X4: Semáforo | Y4: Análisis | Z4: Acción / decisión | AA4: Fecha compromiso
A5: 1.1 | B5: 1. Portafolio Académico | C5: Pertinencia Curricular Internacional | D5: Anual | E5: ≥4/5 | F5: Division of Academic Affairs | J5: =IF(I5="Cumple","🟢",IF(I5="En riesgo","🟡",IF(I5="No cumple","🔴","⚪"))) -> ⚪ | Q5: =IF(P5="Cumple","🟢",IF(P5="En riesgo","🟡",IF(P5="No cumple","🔴","⚪"))) -> ⚪ | X5: =IF(W5="Cumple","🟢",IF(W5="En riesgo","🟡",IF(W5="No cumple","🔴","⚪"))) -> ⚪
A6: 1.2 | B6: 1. Portafolio Académico | C6: Diversificación Lingüística | D6: Anual | E6: ≥30% | F6: Division of Academic Affairs | J6: =IF(I6="Cumple","🟢",IF(I6="En riesgo","🟡",IF(I6="No cumple","🔴","⚪"))) -> ⚪ | Q6: =IF(P6="Cumple","🟢",IF(P6="En riesgo","🟡",IF(P6="No cumple","🔴","⚪"))) -> ⚪ | X6: =IF(W6="Cumple","🟢",IF(W6="En riesgo","🟡",IF(W6="No cumple","🔴","⚪"))) -> ⚪
A7: 1.3 | B7: 1. Portafolio Académico | C7: Innovación Curricular Percibida | D7: Anual | E7: ≥4/5 | F7: Division of Academic Affairs | J7: =IF(I7="Cumple","🟢",IF(I7="En riesgo","🟡",IF(I7="No cumple","🔴","⚪"))) -> ⚪ | Q7: =IF(P7="Cumple","🟢",IF(P7="En riesgo","🟡",IF(P7="No cumple","🔴","⚪"))) -> ⚪ | X7: =IF(W7="Cumple","🟢",IF(W7="En riesgo","🟡",IF(W7="No cumple","🔴","⚪"))) -> ⚪
A8: 1.4 | B8: 1. Portafolio Académico | C8: Flexibilidad Académica | D8: Anual | E8: ≥80% satisfechos | F8: Division of Student Services | J8: =IF(I8="Cumple","🟢",IF(I8="En riesgo","🟡",IF(I8="No cumple","🔴","⚪"))) -> ⚪ | Q8: =IF(P8="Cumple","🟢",IF(P8="En riesgo","🟡",IF(P8="No cumple","🔴","⚪"))) -> ⚪ | X8: =IF(W8="Cumple","🟢",IF(W8="En riesgo","🟡",IF(W8="No cumple","🔴","⚪"))) -> ⚪
A9: 1.5 | B9: 1. Portafolio Académico | C9: Reputación Académica Externa | D9: Anual | E9: ≥4/5 | F9: Division of Academic Affairs | J9: =IF(I9="Cumple","🟢",IF(I9="En riesgo","🟡",IF(I9="No cumple","🔴","⚪"))) -> ⚪ | Q9: =IF(P9="Cumple","🟢",IF(P9="En riesgo","🟡",IF(P9="No cumple","🔴","⚪"))) -> ⚪ | X9: =IF(W9="Cumple","🟢",IF(W9="En riesgo","🟡",IF(W9="No cumple","🔴","⚪"))) -> ⚪
A10: 1.6 | B10: 1. Portafolio Académico | C10: Nº Programas Autorizados (CIE) | D10: Anual | E10: ≥11 | F10: Division of Academic Affairs | J10: =IF(I10="Cumple","🟢",IF(I10="En riesgo","🟡",IF(I10="No cumple","🔴","⚪"))) -> ⚪ | Q10: =IF(P10="Cumple","🟢",IF(P10="En riesgo","🟡",IF(P10="No cumple","🔴","⚪"))) -> ⚪ | X10: =IF(W10="Cumple","🟢",IF(W10="En riesgo","🟡",IF(W10="No cumple","🔴","⚪"))) -> ⚪
A11: 1.7 | B11: 1. Portafolio Académico | C11: Graduation Rate General | D11: Anual | E11: ≥70% | F11: Division of Student Services | J11: =IF(I11="Cumple","🟢",IF(I11="En riesgo","🟡",IF(I11="No cumple","🔴","⚪"))) -> ⚪ | Q11: =IF(P11="Cumple","🟢",IF(P11="En riesgo","🟡",IF(P11="No cumple","🔴","⚪"))) -> ⚪ | X11: =IF(W11="Cumple","🟢",IF(W11="En riesgo","🟡",IF(W11="No cumple","🔴","⚪"))) -> ⚪
A12: 1.8 | B12: 1. Portafolio Académico | C12: Retention Rate Estudiantil | D12: Anual | E12: ≥85% | F12: Division of Student Services | J12: =IF(I12="Cumple","🟢",IF(I12="En riesgo","🟡",IF(I12="No cumple","🔴","⚪"))) -> ⚪ | Q12: =IF(P12="Cumple","🟢",IF(P12="En riesgo","🟡",IF(P12="No cumple","🔴","⚪"))) -> ⚪ | X12: =IF(W12="Cumple","🟢",IF(W12="En riesgo","🟡",IF(W12="No cumple","🔴","⚪"))) -> ⚪
A13: 1.9 | B13: 1. Portafolio Académico | C13: Diversidad Geográfica | D13: Anual | E13: ≥20 países | F13: Division of Admissions/Marketing | J13: =IF(I13="Cumple","🟢",IF(I13="En riesgo","🟡",IF(I13="No cumple","🔴","⚪"))) -> ⚪ | N13: Nº países representados en matrícula | O13: En proceso | P13: CUMPLE | Q13: =IF(P13="Cumple","🟢",IF(P13="En riesgo","🟡",IF(P13="No cumple","🔴","⚪"))) -> 🟢 | R13: está cumpliendo con el indicador, aún está en proceso. el estado actual es de 20 países | S13: continue el indicador | T13: Final de año académico | X13: =IF(W13="Cumple","🟢",IF(W13="En riesgo","🟡",IF(W13="No cumple","🔴","⚪"))) -> ⚪
A14: 1.10 | B14: 1. Portafolio Académico | C14: Oferta Efectiva de Programas | D14: Anual | E14: ≥59% | F14: Division of Admissions/Marketing | J14: =IF(I14="Cumple","🟢",IF(I14="En riesgo","🟡",IF(I14="No cumple","🔴","⚪"))) -> ⚪ | N14: Programas activos/total de oferta | O14: En proceso | P14: CUMPLE | Q14: =IF(P14="Cumple","🟢",IF(P14="En riesgo","🟡",IF(P14="No cumple","🔴","⚪"))) -> 🟢 | R14: Se mantiene al 100%, cumple con el indicador | S14: continue el indicador | T14: Final de año académico | X14: =IF(W14="Cumple","🟢",IF(W14="En riesgo","🟡",IF(W14="No cumple","🔴","⚪"))) -> ⚪
A15: 2.1 | B15: 2. Claustro Académico | C15: Evaluación Docente por Estudiantes | D15: Mensual | E15: ≥4/5 | F15: Division of Student Services | G15: Opinión estudiantil sobre docencia | H15: COMPLETO | I15: CUMPLE | J15: =IF(I15="Cumple","🟢",IF(I15="En riesgo","🟡",IF(I15="No cumple","🔴","⚪"))) -> 🟢 | K15: El promedio es de 4.5 y cumple con la meta esperada | L15: Continuar con las encuestas | M15: - | N15: Opinión estudiantil sobre docencia | O15: En proceso | P15: CUMPLE | Q15: =IF(P15="Cumple","🟢",IF(P15="En riesgo","🟡",IF(P15="No cumple","🔴","⚪"))) -> 🟢 | R15: Se ha recibido un puntaje de 4 ; 5 y 4.62 se considera favorable | S15: continue el indicador | T15: Final del semestre | X15: =IF(W15="Cumple","🟢",IF(W15="En riesgo","🟡",IF(W15="No cumple","🔴","⚪"))) -> ⚪
A16: 2.2 | B16: 2. Claustro Académico | C16: Actualización Pedagógica | D16: Anual | E16: ≥70% | F16: Division of Continuing Education/Division of Academic Affairs | J16: =IF(I16="Cumple","🟢",IF(I16="En riesgo","🟡",IF(I16="No cumple","🔴","⚪"))) -> ⚪ | Q16: =IF(P16="Cumple","🟢",IF(P16="En riesgo","🟡",IF(P16="No cumple","🔴","⚪"))) -> ⚪ | X16: =IF(W16="Cumple","🟢",IF(W16="En riesgo","🟡",IF(W16="No cumple","🔴","⚪"))) -> ⚪
A17: 2.3 | B17: 2. Claustro Académico | C17: Diversidad Internacional | D17: Anual | E17: ≥10 países | F17: Division of Academic Affairs | J17: =IF(I17="Cumple","🟢",IF(I17="En riesgo","🟡",IF(I17="No cumple","🔴","⚪"))) -> ⚪ | Q17: =IF(P17="Cumple","🟢",IF(P17="En riesgo","🟡",IF(P17="No cumple","🔴","⚪"))) -> ⚪ | X17: =IF(W17="Cumple","🟢",IF(W17="En riesgo","🟡",IF(W17="No cumple","🔴","⚪"))) -> ⚪
A18: 2.4 | B18: 2. Claustro Académico | C18: Innovación Didáctica | D18: Anual | E18: ≥4/5 | F18: Division of Academic Affairs | J18: =IF(I18="Cumple","🟢",IF(I18="En riesgo","🟡",IF(I18="No cumple","🔴","⚪"))) -> ⚪ | Q18: =IF(P18="Cumple","🟢",IF(P18="En riesgo","🟡",IF(P18="No cumple","🔴","⚪"))) -> ⚪ | X18: =IF(W18="Cumple","🟢",IF(W18="En riesgo","🟡",IF(W18="No cumple","🔴","⚪"))) -> ⚪
A19: 2.5 | B19: 2. Claustro Académico | C19: Reconocimiento Externo del Claustro | D19: Anual | E19: ≥4/5 | F19: Division of Academic Affairs | J19: =IF(I19="Cumple","🟢",IF(I19="En riesgo","🟡",IF(I19="No cumple","🔴","⚪"))) -> ⚪ | Q19: =IF(P19="Cumple","🟢",IF(P19="En riesgo","🟡",IF(P19="No cumple","🔴","⚪"))) -> ⚪ | X19: =IF(W19="Cumple","🟢",IF(W19="En riesgo","🟡",IF(W19="No cumple","🔴","⚪"))) -> ⚪
A20: 2.6 | B20: 2. Claustro Académico | C20: % Profesores Top en Actividad | D20: Anual | E20: ≥10% | F20: Division of Academic Affairs | J20: =IF(I20="Cumple","🟢",IF(I20="En riesgo","🟡",IF(I20="No cumple","🔴","⚪"))) -> ⚪ | Q20: =IF(P20="Cumple","🟢",IF(P20="En riesgo","🟡",IF(P20="No cumple","🔴","⚪"))) -> ⚪ | X20: =IF(W20="Cumple","🟢",IF(W20="En riesgo","🟡",IF(W20="No cumple","🔴","⚪"))) -> ⚪
A21: 2.7 | B21: 2. Claustro Académico | C21: Permanencia Docente | D21: Anual | E21: ≥85% | F21: Division of Academic Affairs | J21: =IF(I21="Cumple","🟢",IF(I21="En riesgo","🟡",IF(I21="No cumple","🔴","⚪"))) -> ⚪ | Q21: =IF(P21="Cumple","🟢",IF(P21="En riesgo","🟡",IF(P21="No cumple","🔴","⚪"))) -> ⚪ | X21: =IF(W21="Cumple","🟢",IF(W21="En riesgo","🟡",IF(W21="No cumple","🔴","⚪"))) -> ⚪
A22: 2.8 | B22: 2. Claustro Académico | C22: Producción Científica | D22: Anual | E22: ≥2 | F22: Division of Academic Affairs | J22: =IF(I22="Cumple","🟢",IF(I22="En riesgo","🟡",IF(I22="No cumple","🔴","⚪"))) -> ⚪ | Q22: =IF(P22="Cumple","🟢",IF(P22="En riesgo","🟡",IF(P22="No cumple","🔴","⚪"))) -> ⚪ | X22: =IF(W22="Cumple","🟢",IF(W22="En riesgo","🟡",IF(W22="No cumple","🔴","⚪"))) -> ⚪
A23: 2.9 | B23: 2. Claustro Académico | C23: Satisfacción Académica | D23: Anual | E23: ≥80% satisfechos | F23: Division of Student Services | J23: =IF(I23="Cumple","🟢",IF(I23="En riesgo","🟡",IF(I23="No cumple","🔴","⚪"))) -> ⚪ | Q23: =IF(P23="Cumple","🟢",IF(P23="En riesgo","🟡",IF(P23="No cumple","🔴","⚪"))) -> ⚪ | X23: =IF(W23="Cumple","🟢",IF(W23="En riesgo","🟡",IF(W23="No cumple","🔴","⚪"))) -> ⚪
A24: 2.10 | B24: 2. Claustro Académico | C24: Graduation Rate Posgrado | D24: Anual | E24: ≥70% | F24: Division of Student Services | J24: =IF(I24="Cumple","🟢",IF(I24="En riesgo","🟡",IF(I24="No cumple","🔴","⚪"))) -> ⚪ | Q24: =IF(P24="Cumple","🟢",IF(P24="En riesgo","🟡",IF(P24="No cumple","🔴","⚪"))) -> ⚪ | X24: =IF(W24="Cumple","🟢",IF(W24="En riesgo","🟡",IF(W24="No cumple","🔴","⚪"))) -> ⚪
A25: 3.1 | B25: 3. Capital Humano (Administrativo) | C25: Satisfacción con Central de Atención | D25: Anual | E25: ≥4/5 | F25: Division of Student Services | J25: =IF(I25="Cumple","🟢",IF(I25="En riesgo","🟡",IF(I25="No cumple","🔴","⚪"))) -> ⚪ | Q25: =IF(P25="Cumple","🟢",IF(P25="En riesgo","🟡",IF(P25="No cumple","🔴","⚪"))) -> ⚪ | X25: =IF(W25="Cumple","🟢",IF(W25="En riesgo","🟡",IF(W25="No cumple","🔴","⚪"))) -> ⚪
A26: 3.2 | B26: 3. Capital Humano (Administrativo) | C26: Innovación Administrativa | D26: Anual | E26: ≥6 | F26: Division of Administration Services and Finance | J26: =IF(I26="Cumple","🟢",IF(I26="En riesgo","🟡",IF(I26="No cumple","🔴","⚪"))) -> ⚪ | Q26: =IF(P26="Cumple","🟢",IF(P26="En riesgo","🟡",IF(P26="No cumple","🔴","⚪"))) -> ⚪ | X26: =IF(W26="Cumple","🟢",IF(W26="En riesgo","🟡",IF(W26="No cumple","🔴","⚪"))) -> ⚪
A27: 3.3 | B27: 3. Capital Humano (Administrativo) | C27: Accesibilidad de Servicios | D27: Anual | E27: ≥85% | F27: Division of Administration Services and Finance | J27: =IF(I27="Cumple","🟢",IF(I27="En riesgo","🟡",IF(I27="No cumple","🔴","⚪"))) -> ⚪ | Q27: =IF(P27="Cumple","🟢",IF(P27="En riesgo","🟡",IF(P27="No cumple","🔴","⚪"))) -> ⚪ | X27: =IF(W27="Cumple","🟢",IF(W27="En riesgo","🟡",IF(W27="No cumple","🔴","⚪"))) -> ⚪
A28: 3.4 | B28: 3. Capital Humano (Administrativo) | C28: Clima Laboral Administrativo | D28: Anual | E28: ≥85% | F28: Division of Administration Services and Finance | J28: =IF(I28="Cumple","🟢",IF(I28="En riesgo","🟡",IF(I28="No cumple","🔴","⚪"))) -> ⚪ | N28: Opinión del staff | O28: EN LEVANTAMIENTO | P28: PENDIENTE | Q28: =IF(P28="Cumple","🟢",IF(P28="En riesgo","🟡",IF(P28="No cumple","🔴","⚪"))) -> ⚪ | R28: Se envío evidencia de los resultados de la encuesta | S28: Continuar | T28: Final de año académico | X28: =IF(W28="Cumple","🟢",IF(W28="En riesgo","🟡",IF(W28="No cumple","🔴","⚪"))) -> ⚪
A29: 3.5 | B29: 3. Capital Humano (Administrativo) | C29: Imagen Institucional Administrativa | D29: Anual | E29: ≥85% | F29: Division of Administration Services and Finance | J29: =IF(I29="Cumple","🟢",IF(I29="En riesgo","🟡",IF(I29="No cumple","🔴","⚪"))) -> ⚪ | Q29: =IF(P29="Cumple","🟢",IF(P29="En riesgo","🟡",IF(P29="No cumple","🔴","⚪"))) -> ⚪ | X29: =IF(W29="Cumple","🟢",IF(W29="En riesgo","🟡",IF(W29="No cumple","🔴","⚪"))) -> ⚪
A30: 3.6 | B30: 3. Capital Humano (Administrativo) | C30: Capacitación Administrativa | D30: Anual | E30: ≥80% | F30: Division of Administration Services and Finance | J30: =IF(I30="Cumple","🟢",IF(I30="En riesgo","🟡",IF(I30="No cumple","🔴","⚪"))) -> ⚪ | Q30: =IF(P30="Cumple","🟢",IF(P30="En riesgo","🟡",IF(P30="No cumple","🔴","⚪"))) -> ⚪ | X30: =IF(W30="Cumple","🟢",IF(W30="En riesgo","🟡",IF(W30="No cumple","🔴","⚪"))) -> ⚪
A31: 3.7 | B31: 3. Capital Humano (Administrativo) | C31: Resolución en Primer Contacto | D31: Anual | E31: ≥70% | F31: Division of Administration Services and Finance | J31: =IF(I31="Cumple","🟢",IF(I31="En riesgo","🟡",IF(I31="No cumple","🔴","⚪"))) -> ⚪ | Q31: =IF(P31="Cumple","🟢",IF(P31="En riesgo","🟡",IF(P31="No cumple","🔴","⚪"))) -> ⚪ | X31: =IF(W31="Cumple","🟢",IF(W31="En riesgo","🟡",IF(W31="No cumple","🔴","⚪"))) -> ⚪
A32: 3.8 | B32: 3. Capital Humano (Administrativo) | C32: Tiempo Medio de Respuesta | D32: Anual | E32: ≤6h | F32: Division of Administration Services and Finance | J32: =IF(I32="Cumple","🟢",IF(I32="En riesgo","🟡",IF(I32="No cumple","🔴","⚪"))) -> ⚪ | Q32: =IF(P32="Cumple","🟢",IF(P32="En riesgo","🟡",IF(P32="No cumple","🔴","⚪"))) -> ⚪ | X32: =IF(W32="Cumple","🟢",IF(W32="En riesgo","🟡",IF(W32="No cumple","🔴","⚪"))) -> ⚪
A33: 3.9 | B33: 3. Capital Humano (Administrativo) | C33: Retention Rate Administrativo | D33: Anual | E33: ≥85% | F33: Division of Administration Services and Finance | J33: =IF(I33="Cumple","🟢",IF(I33="En riesgo","🟡",IF(I33="No cumple","🔴","⚪"))) -> ⚪ | Q33: =IF(P33="Cumple","🟢",IF(P33="En riesgo","🟡",IF(P33="No cumple","🔴","⚪"))) -> ⚪ | X33: =IF(W33="Cumple","🟢",IF(W33="En riesgo","🟡",IF(W33="No cumple","🔴","⚪"))) -> ⚪
A34: 3.10 | B34: 3. Capital Humano (Administrativo) | C34: Satisfacción con Servicios Administrativos | D34: Anual | E34: ≥80% | F34: Division of Administration Services and Finance | J34: =IF(I34="Cumple","🟢",IF(I34="En riesgo","🟡",IF(I34="No cumple","🔴","⚪"))) -> ⚪ | Q34: =IF(P34="Cumple","🟢",IF(P34="En riesgo","🟡",IF(P34="No cumple","🔴","⚪"))) -> ⚪ | X34: =IF(W34="Cumple","🟢",IF(W34="En riesgo","🟡",IF(W34="No cumple","🔴","⚪"))) -> ⚪
A35: 4.1 | B35: 4. Plataformas Tecnológicas | C35: Satisfacción General con Plataformas (LMS/SIS) | D35: Anual | E35: ≥4/5 | F35: Division of Student Services / Division of Academic Affairs | J35: =IF(I35="Cumple","🟢",IF(I35="En riesgo","🟡",IF(I35="No cumple","🔴","⚪"))) -> ⚪ | Q35: =IF(P35="Cumple","🟢",IF(P35="En riesgo","🟡",IF(P35="No cumple","🔴","⚪"))) -> ⚪ | X35: =IF(W35="Cumple","🟢",IF(W35="En riesgo","🟡",IF(W35="No cumple","🔴","⚪"))) -> ⚪
A36: 4.2 | B36: 4. Plataformas Tecnológicas | C36: Seguridad Percibida | D36: Anual | E36: ≥90% | F36: Division of Student Services / Division of Academic Affairs | J36: =IF(I36="Cumple","🟢",IF(I36="En riesgo","🟡",IF(I36="No cumple","🔴","⚪"))) -> ⚪ | Q36: =IF(P36="Cumple","🟢",IF(P36="En riesgo","🟡",IF(P36="No cumple","🔴","⚪"))) -> ⚪ | X36: =IF(W36="Cumple","🟢",IF(W36="En riesgo","🟡",IF(W36="No cumple","🔴","⚪"))) -> ⚪
A37: 4.3 | B37: 4. Plataformas Tecnológicas | C37: Innovación Tecnológica Percibida | D37: Anual | E37: ≥4/5 | F37: Division of Student Services / Division of Academic Affairs | J37: =IF(I37="Cumple","🟢",IF(I37="En riesgo","🟡",IF(I37="No cumple","🔴","⚪"))) -> ⚪ | Q37: =IF(P37="Cumple","🟢",IF(P37="En riesgo","🟡",IF(P37="No cumple","🔴","⚪"))) -> ⚪ | X37: =IF(W37="Cumple","🟢",IF(W37="En riesgo","🟡",IF(W37="No cumple","🔴","⚪"))) -> ⚪
A38: 4.4 | B38: 4. Plataformas Tecnológicas | C38: Disponibilidad de Sistemas Críticos (Uptime) | D38: Mensual | E38: ≥99,9% | F38: Division of Administration Services and Finance | G38: el promedio acumulado o el último valor consolidado del periodo; | H38: COMPLETO | I38: CUMPLE | J38: =IF(I38="Cumple","🟢",IF(I38="En riesgo","🟡",IF(I38="No cumple","🔴","⚪"))) -> 🟢 | K38: Uptime promedio al corte: LMS 99,99% / SIS 99,95% | L38: Mantener seguimiento mensual. | M38: - | N38: el promedio acumulado o el último valor consolidado del periodo; | O38: COMPLETO | P38: CUMPLE | Q38: =IF(P38="Cumple","🟢",IF(P38="En riesgo","🟡",IF(P38="No cumple","🔴","⚪"))) -> 🟢 | R38: Promedio LMS: 99.99% Promedio SIS: 99.98% | S38: Mantener seguimiento mensual. | T38: - | X38: =IF(W38="Cumple","🟢",IF(W38="En riesgo","🟡",IF(W38="No cumple","🔴","⚪"))) -> ⚪
A39: 4.5 | B39: 4. Plataformas Tecnológicas | C39: Optimización de Procesos | D39: Anual | E39: ≥5 nuevos/año | F39: Division of Administration Services and Finance | J39: =IF(I39="Cumple","🟢",IF(I39="En riesgo","🟡",IF(I39="No cumple","🔴","⚪"))) -> ⚪ | Q39: =IF(P39="Cumple","🟢",IF(P39="En riesgo","🟡",IF(P39="No cumple","🔴","⚪"))) -> ⚪ | X39: =IF(W39="Cumple","🟢",IF(W39="En riesgo","🟡",IF(W39="No cumple","🔴","⚪"))) -> ⚪
A40: 4.6 | B40: 4. Plataformas Tecnológicas | C40: Adopción y Capacitación en Plataformas | D40: Anual | E40: ≥90% | F40: Division of Academic Affairs / Division of Continuing Education | J40: =IF(I40="Cumple","🟢",IF(I40="En riesgo","🟡",IF(I40="No cumple","🔴","⚪"))) -> ⚪ | Q40: =IF(P40="Cumple","🟢",IF(P40="En riesgo","🟡",IF(P40="No cumple","🔴","⚪"))) -> ⚪ | X40: =IF(W40="Cumple","🟢",IF(W40="En riesgo","🟡",IF(W40="No cumple","🔴","⚪"))) -> ⚪
A41: 4.7 | B41: 4. Plataformas Tecnológicas | C41: Costo de Tecnología por Estudiante | D41: Semestral | E41: ≤USD 500 | F41: Division of Administration Services and Finance | G41: Gasto total en infraestructura y licencias tecnológicas por estudiante. | H41: COMPLETO | I41: CUMPLE | J41: =IF(I41="Cumple","🟢",IF(I41="En riesgo","🟡",IF(I41="No cumple","🔴","⚪"))) -> 🟢 | K41: 4.95 $ es menor a USD 500 | L41: Mantener seguimiento semestral. | M41: - | N41: Gasto total en infraestructura y licencias tecnológicas por estudiante. | O41: COMPLETO | P41: CUMPLE | Q41: =IF(P41="Cumple","🟢",IF(P41="En riesgo","🟡",IF(P41="No cumple","🔴","⚪"))) -> 🟢 | R41: 9.80 USD es menor a USD 500 | S41: Mantener seguimiento semestral. | T41: - | X41: =IF(W41="Cumple","🟢",IF(W41="En riesgo","🟡",IF(W41="No cumple","🔴","⚪"))) -> ⚪
A42: 5.1 | B42: 5. Posicionamiento Global | C42: Relevancia de Alianzas | D42: Anual | E42: ≥4/5 | F42: Division of Admissions/Marketing | J42: =IF(I42="Cumple","🟢",IF(I42="En riesgo","🟡",IF(I42="No cumple","🔴","⚪"))) -> ⚪ | N42: Impacto académico de convenios | O42: EN PROCESO | P42: En riesgo | Q42: =IF(P42="Cumple","🟢",IF(P42="En riesgo","🟡",IF(P42="No cumple","🔴","⚪"))) -> 🟡 | R42: Hasta el momento va 1 de 5 Contamos con 4 convenios activos de los cuales 1 ofrece impacto a nivel matrículas con un 73% de la participación en matriculas de pregrado. | T42: Final de año académico | X42: =IF(W42="Cumple","🟢",IF(W42="En riesgo","🟡",IF(W42="No cumple","🔴","⚪"))) -> ⚪
A43: 5.2 | B43: 5. Posicionamiento Global | C43: Percepción de Marca Global | D43: Anual | E43: ≥60% | F43: Division of Admissions/Marketing | J43: =IF(I43="Cumple","🟢",IF(I43="En riesgo","🟡",IF(I43="No cumple","🔴","⚪"))) -> ⚪ | N43: Opinión sobre visibilidad internacional Asociación de marca | O43: EN PROCESO | P43: - | Q43: =IF(P43="Cumple","🟢",IF(P43="En riesgo","🟡",IF(P43="No cumple","🔴","⚪"))) -> ⚪ | R43: En las encuestas que se han aplicado hasta el momento (registros, servicios al estudiante y marketing) no se ha considerado el item | S43: Incluirlo en la encuesta del proximo semestre | T43: Final de año académico | X43: =IF(W43="Cumple","🟢",IF(W43="En riesgo","🟡",IF(W43="No cumple","🔴","⚪"))) -> ⚪
A44: 5.3 | B44: 5. Posicionamiento Global | C44: Satisfacción de Socios | D44: Anual | E44: ≥4/5 | F44: Division of Student Services | J44: =IF(I44="Cumple","🟢",IF(I44="En riesgo","🟡",IF(I44="No cumple","🔴","⚪"))) -> ⚪ | Q44: =IF(P44="Cumple","🟢",IF(P44="En riesgo","🟡",IF(P44="No cumple","🔴","⚪"))) -> ⚪ | X44: =IF(W44="Cumple","🟢",IF(W44="En riesgo","🟡",IF(W44="No cumple","🔴","⚪"))) -> ⚪
A45: 5.4 | B45: 5. Posicionamiento Global | C45: Reconocimiento en Rankings | D45: Anual | E45: Aparecer en un ranking | F45: Division of Admissions/Marketing | J45: =IF(I45="Cumple","🟢",IF(I45="En riesgo","🟡",IF(I45="No cumple","🔴","⚪"))) -> ⚪ | N45: Posición en rankings | O45: EN PROCESO | P45: En riesgo | Q45: =IF(P45="Cumple","🟢",IF(P45="En riesgo","🟡",IF(P45="No cumple","🔴","⚪"))) -> 🟡 | R45: El resultado es de 0 | S45: Si no se presentan buenos resultados, sacar el indicador | T45: Final de año académico | X45: =IF(W45="Cumple","🟢",IF(W45="En riesgo","🟡",IF(W45="No cumple","🔴","⚪"))) -> ⚪
A46: 5.6 | B46: 5. Posicionamiento Global | C46: Nº Alianzas Firmadas | D46: Anual | E46: ≥20 | F46: Division of Admissions/Marketing | J46: =IF(I46="Cumple","🟢",IF(I46="En riesgo","🟡",IF(I46="No cumple","🔴","⚪"))) -> ⚪ | N46: Cantidad de convenios activos | O46: EN PROCESO | P46: En riesgo | Q46: =IF(P46="Cumple","🟢",IF(P46="En riesgo","🟡",IF(P46="No cumple","🔴","⚪"))) -> 🟡 | R46: El resultado es de 4, está muy por debajo de 20 que es la meta | S46: se ha incorporado una ejecutiva de convenios | T46: Final de año académico | X46: =IF(W46="Cumple","🟢",IF(W46="En riesgo","🟡",IF(W46="No cumple","🔴","⚪"))) -> ⚪
A47: 5.7 | B47: 5. Posicionamiento Global | C47: Nº Estudiantes en Movilidad | D47: Anual | E47: ≥50 | F47: Division of Student Services | J47: =IF(I47="Cumple","🟢",IF(I47="En riesgo","🟡",IF(I47="No cumple","🔴","⚪"))) -> ⚪ | Q47: =IF(P47="Cumple","🟢",IF(P47="En riesgo","🟡",IF(P47="No cumple","🔴","⚪"))) -> ⚪ | X47: =IF(W47="Cumple","🟢",IF(W47="En riesgo","🟡",IF(W47="No cumple","🔴","⚪"))) -> ⚪
A48: 5.8 | B48: 5. Posicionamiento Global | C48: Placement Rate | D48: Semestral | E48: ≥85% | F48: Division of Student Services | G48: Inserción laboral graduados | H48: COMPLETO | I48: NO CUMPLE | J48: =IF(I48="Cumple","🟢",IF(I48="En riesgo","🟡",IF(I48="No cumple","🔴","⚪"))) -> 🔴 | K48: El resultado es del 72% siendo menor a la meta del 85 % | L48: Se contrato un ejecutivo de seguimiento al egresado | M48: - | N48: Inserción laboral graduados | O48: EN LEVANTAMIENTO | Q48: =IF(P48="Cumple","🟢",IF(P48="En riesgo","🟡",IF(P48="No cumple","🔴","⚪"))) -> ⚪ | R48: Falta el dato del mes de abril para realizar una evaluacion | T48: 46150 | X48: =IF(W48="Cumple","🟢",IF(W48="En riesgo","🟡",IF(W48="No cumple","🔴","⚪"))) -> ⚪
A49: 5.9 | B49: 5. Posicionamiento Global | C49: Visibilidad Académica | D49: Semestral | E49: ≥12 | F49: Division of Academic Affairs | J49: =IF(I49="Cumple","🟢",IF(I49="En riesgo","🟡",IF(I49="No cumple","🔴","⚪"))) -> ⚪ | Q49: =IF(P49="Cumple","🟢",IF(P49="En riesgo","🟡",IF(P49="No cumple","🔴","⚪"))) -> ⚪ | X49: =IF(W49="Cumple","🟢",IF(W49="En riesgo","🟡",IF(W49="No cumple","🔴","⚪"))) -> ⚪
A50: 5.10 | B50: 5. Posicionamiento Global | C50: Membresías Internacionales | D50: Anual | E50: ≥6 | F50: Division of Administration Services and Finance | J50: =IF(I50="Cumple","🟢",IF(I50="En riesgo","🟡",IF(I50="No cumple","🔴","⚪"))) -> ⚪ | Q50: =IF(P50="Cumple","🟢",IF(P50="En riesgo","🟡",IF(P50="No cumple","🔴","⚪"))) -> ⚪ | X50: =IF(W50="Cumple","🟢",IF(W50="En riesgo","🟡",IF(W50="No cumple","🔴","⚪"))) -> ⚪
A51: 6.1 | B51: 6. Cultura Universitaria | C51: Índice de Formación Integral | D51: Anual | E51: ≥4/5 | F51: Division of Student Services | J51: =IF(I51="Cumple","🟢",IF(I51="En riesgo","🟡",IF(I51="No cumple","🔴","⚪"))) -> ⚪ | Q51: =IF(P51="Cumple","🟢",IF(P51="En riesgo","🟡",IF(P51="No cumple","🔴","⚪"))) -> ⚪ | X51: =IF(W51="Cumple","🟢",IF(W51="En riesgo","🟡",IF(W51="No cumple","🔴","⚪"))) -> ⚪
A52: 6.2 | B52: 6. Cultura Universitaria | C52: Inclusión y Diversidad Percibida | D52: Anual | E52: ≥85% | F52: Division of Student Services | J52: =IF(I52="Cumple","🟢",IF(I52="En riesgo","🟡",IF(I52="No cumple","🔴","⚪"))) -> ⚪ | Q52: =IF(P52="Cumple","🟢",IF(P52="En riesgo","🟡",IF(P52="No cumple","🔴","⚪"))) -> ⚪ | X52: =IF(W52="Cumple","🟢",IF(W52="En riesgo","🟡",IF(W52="No cumple","🔴","⚪"))) -> ⚪
A53: 6.3 | B53: 6. Cultura Universitaria | C53: Participación en Actividades Culturales | D53: Anual | E53: ≥4/5 | F53: Division of Student Services | J53: =IF(I53="Cumple","🟢",IF(I53="En riesgo","🟡",IF(I53="No cumple","🔴","⚪"))) -> ⚪ | Q53: =IF(P53="Cumple","🟢",IF(P53="En riesgo","🟡",IF(P53="No cumple","🔴","⚪"))) -> ⚪ | X53: =IF(W53="Cumple","🟢",IF(W53="En riesgo","🟡",IF(W53="No cumple","🔴","⚪"))) -> ⚪
A54: 6.4 | B54: 6. Cultura Universitaria | C54: Clima Ético Universitario | D54: Anual | E54: ≥90% | F54: Division of Student Services | J54: =IF(I54="Cumple","🟢",IF(I54="En riesgo","🟡",IF(I54="No cumple","🔴","⚪"))) -> ⚪ | Q54: =IF(P54="Cumple","🟢",IF(P54="En riesgo","🟡",IF(P54="No cumple","🔴","⚪"))) -> ⚪ | X54: =IF(W54="Cumple","🟢",IF(W54="En riesgo","🟡",IF(W54="No cumple","🔴","⚪"))) -> ⚪
A55: 6.5 | B55: 6. Cultura Universitaria | C55: Sentido de Pertenencia | D55: Anual | E55: ≥85% | F55: Division of Student Services | J55: =IF(I55="Cumple","🟢",IF(I55="En riesgo","🟡",IF(I55="No cumple","🔴","⚪"))) -> ⚪ | Q55: =IF(P55="Cumple","🟢",IF(P55="En riesgo","🟡",IF(P55="No cumple","🔴","⚪"))) -> ⚪ | X55: =IF(W55="Cumple","🟢",IF(W55="En riesgo","🟡",IF(W55="No cumple","🔴","⚪"))) -> ⚪
A56: 6.6 | B56: 6. Cultura Universitaria | C56: Participación en Cultura BGU | D56: Anual | E56: ≥30% | F56: Division of Student Services | J56: =IF(I56="Cumple","🟢",IF(I56="En riesgo","🟡",IF(I56="No cumple","🔴","⚪"))) -> ⚪ | Q56: =IF(P56="Cumple","🟢",IF(P56="En riesgo","🟡",IF(P56="No cumple","🔴","⚪"))) -> ⚪ | X56: =IF(W56="Cumple","🟢",IF(W56="En riesgo","🟡",IF(W56="No cumple","🔴","⚪"))) -> ⚪
A57: 6.7 | B57: 6. Cultura Universitaria | C57: Nº Actividades Inclusión y Diversidad | D57: Anual | E57: ≥4 | F57: Division of Student Services | J57: =IF(I57="Cumple","🟢",IF(I57="En riesgo","🟡",IF(I57="No cumple","🔴","⚪"))) -> ⚪ | Q57: =IF(P57="Cumple","🟢",IF(P57="En riesgo","🟡",IF(P57="No cumple","🔴","⚪"))) -> ⚪ | X57: =IF(W57="Cumple","🟢",IF(W57="En riesgo","🟡",IF(W57="No cumple","🔴","⚪"))) -> ⚪
A58: 6.8 | B58: 6. Cultura Universitaria | C58: Voluntariado Estudiantil | D58: Anual | E58: ≥50 | F58: Division of Student Services | J58: =IF(I58="Cumple","🟢",IF(I58="En riesgo","🟡",IF(I58="No cumple","🔴","⚪"))) -> ⚪ | Q58: =IF(P58="Cumple","🟢",IF(P58="En riesgo","🟡",IF(P58="No cumple","🔴","⚪"))) -> ⚪ | X58: =IF(W58="Cumple","🟢",IF(W58="En riesgo","🟡",IF(W58="No cumple","🔴","⚪"))) -> ⚪
A59: 6.10 | B59: 6. Cultura Universitaria | C59: Student Satisfaction Rate (Cultura) | D59: Anual | E59: ≥80% | F59: Division of Student Services | J59: =IF(I59="Cumple","🟢",IF(I59="En riesgo","🟡",IF(I59="No cumple","🔴","⚪"))) -> ⚪ | Q59: =IF(P59="Cumple","🟢",IF(P59="En riesgo","🟡",IF(P59="No cumple","🔴","⚪"))) -> ⚪ | X59: =IF(W59="Cumple","🟢",IF(W59="En riesgo","🟡",IF(W59="No cumple","🔴","⚪"))) -> ⚪
A60: 7.1 | B60: 7. Apoyo Económico | C60: Satisfacción con Becas y Apoyo Económico | D60: Anual | E60: Opinión favorable | F60: Division of Student Services | J60: =IF(I60="Cumple","🟢",IF(I60="En riesgo","🟡",IF(I60="No cumple","🔴","⚪"))) -> ⚪ | Q60: =IF(P60="Cumple","🟢",IF(P60="En riesgo","🟡",IF(P60="No cumple","🔴","⚪"))) -> ⚪ | X60: =IF(W60="Cumple","🟢",IF(W60="En riesgo","🟡",IF(W60="No cumple","🔴","⚪"))) -> ⚪
... A68: 7.10 | B68: 7. Apoyo Económico | C68: Graduation Rate Becados | D68: Anual | E68: ≥70% | F68: Division of Student Services | J68: =IF(I68="Cumple","🟢",IF(I68="En riesgo","🟡",IF(I68="No cumple","🔴","⚪"))) -> ⚪ | Q68: =IF(P68="Cumple","🟢",IF(P68="En riesgo","🟡",IF(P68="No cumple","🔴","⚪"))) -> ⚪ | X68: =IF(W68="Cumple","🟢",IF(W68="En riesgo","🟡",IF(W68="No cumple","🔴","⚪"))) -> ⚪
B76: 1. Valor del corte
B78: Aquí va el dato disponible al momento de diciembre.
B80: Ejemplos:
B82: si es mensual: el promedio acumulado o el último valor consolidado del periodo; | I82: Criterio sugerido de evaluación
B83: si es semestral: avance preliminar o “sin cierre semestral aún”;
B84: si es anual: normalmente no va valor final, salvo que ya exista evidencia preliminar. | I84: Temporalidad | J84: Qué registrar | K84: Qué analizar en los cortes
I85: Mensual | J85: Dato de cada mes | K85: Analiza tendencia acumulada en C1, C2 y C3
B86: Ejemplo: | I86: Semestral | J86: Dato al cierre de cada semestre | K86: En C1 usa avance preliminar si aplica; en C2 y C3 incorpora cierres semestrales
I87: Anual | J87: Dato una vez por año | K87: En C1/C2 deja evidencia del levantamiento; en C3 emite juicio final
B88: 4.4 Uptime: LMS 99.99% / SIS 99.95%
B89: 2.1 Evaluación Docente: 4.3/5
B90: 2. Estado del dato
B92: Aquí dices en qué condición está el indicador al corte.
B94: Opciones útiles:
B96: Completo
B97: Parcial
B98: En levantamiento
B99: Pendiente
B100: Preliminar
B101: No aplica al corte
B103: Ejemplos:
... B180: anuales: fecha de levantamiento o consolidación, normalmente hacia abril o agosto

Sheet Actas
A2: ACADEMIC TERM | B2: EVIDENCIAS | C2: ENLACES
A3: FALL | B3: EVALUACIÓN DE FALL 2025 - 2026 (INGLÉS) | C3: Evaluation_Report_IEP_Fall_2025.docx
B4: EVALUACIÓN DE FALL 2025 - 2026 (ESPAÑOL) | C4: Informe_Evaluacion_Plan_Efectividad_Fall_2025.docx
B5: PRESIDENT'S REPORT - FALL 2025 - 2026 ACADEMIC TERM | C5: Presidents_Report_Fall_2025_Academic_Term.docx
B6: RESULTADOS DEL INSTITUTIONAL EFFECTIVENESS PLAN EVALUATION FALL 2025 - 2026 | C6: Results_IEP_Evaluation_Fall_2025_President.docx
A7: SPRING | B7: EVALUACIÓN DE SPRING 2025 - 2026 (INGLÉS) | C7: Evaluation Report on the Execution Results of the Institutional Effectiveness Plan Spring 2026
B8: EVALUACIÓN DE SPRING 2025 - 2026 (ESPAÑOL) | C8: Informe de Evaluación de Resultados de la Ejecución del Plan de Efectividad Institucional - SPRING
B9: PRESIDENT'S REPORT - SPRING 2025 - 2026 ACADEMIC TERM | C9: President’s Report – Spring 2026 Academic Term
B10: RESULTADOS DEL INSTITUTIONAL EFFECTIVENESS PLAN EVALUATION SPRING 2025 - 2026 | C10: Results of the Institutional Effectiveness Plan Evaluation - Spring 2026 Academic Term - President
A11: SUMMER | B11: EVALUACIÓN DE SUMMER 2025 - 2026 (INGLÉS)
B12: EVALUACIÓN DE SUMMER 2025 - 2026 (ESPAÑOL)
B13: PRESIDENT'S REPORT - SUMMER 2025 - 2026 ACADEMIC TERM
B14: RESULTADOS DEL INSTITUTIONAL EFFECTIVENESS PLAN EVALUATION SUMMER 2025 - 2026
A15: ANUAL

Sheet Indicadores Master
A1: Dimensión | B1: Objetivo Institucional | C1: Tipo | D1: Código | E1: Indicador | F1: Descripción | G1: Fórmula de Cálculo | H1: Meta Esperada | I1: Fuente de Verificación | J1: División BGU | K1: Temporalidad | L1: Criterio C1 | M1: Criterio C2 | N1: Criterio C3
A2: 1. Portafolio Académico | B2: Establecer una comunidad de aprendizaje diversa y global, mediante programas académicos y de educación continua en diversos idiomas. | C2: Cualitativo | D2: 1.1 | E2: Pertinencia Curricular Internacional | F2: Evalúa la alineación de programas con demandas globales | G2: Rúbrica documental (1–5) | H2: ≥4/5 | I2: Informes de revisión curricular | J2: Division of Academic Affairs | K2: Anual | L2: En levantamiento o pendiente de medición anual | M2: Avance del levantamiento / revisión de evidencia | N2: Emitir evaluación final anual
A3: 1. Portafolio Académico | B3: Establecer una comunidad de aprendizaje diversa y global, mediante programas académicos y de educación continua en diversos idiomas. | C3: Cualitativo | D3: 1.2 | E3: Diversificación Lingüística | F3: Mide idiomas en que se ofrecen programas | G3: Programas en otros idiomas / total ×100 | H3: ≥30% | I3: Oferta académica oficial | J3: Division of Academic Affairs | K3: Anual | L3: En levantamiento o pendiente de medición anual | M3: Avance del levantamiento / revisión de evidencia | N3: Emitir evaluación final anual
A4: 1. Portafolio Académico | B4: Establecer una comunidad de aprendizaje diversa y global, mediante programas académicos y de educación continua en diversos idiomas. | C4: Cualitativo | D4: 1.3 | E4: Innovación Curricular Percibida | F4: Opinión sobre innovación curricular | G4: Encuesta Likert (1–5) | H4: ≥4/5 | I4: Encuestas a estudiantes y docentes | J4: Division of Academic Affairs | K4: Anual | L4: En levantamiento o pendiente de medición anual | M4: Avance del levantamiento / revisión de evidencia | N4: Emitir evaluación final anual
A5: 1. Portafolio Académico | B5: Establecer una comunidad de aprendizaje diversa y global, mediante programas académicos y de educación continua en diversos idiomas. | C5: Cualitativo | D5: 1.4 | E5: Flexibilidad Académica | F5: Satisfacción con modalidades (online) | G5: Encuesta de satisfacción (1–5) | H5: ≥80% satisfechos | I5: Encuestas institucionales | J5: Division of Student Services | K5: Anual | L5: En levantamiento o pendiente de medición anual | M5: Avance del levantamiento / revisión de evidencia | N5: Emitir evaluación final anual
A6: 1. Portafolio Académico | B6: Establecer una comunidad de aprendizaje diversa y global, mediante programas académicos y de educación continua en diversos idiomas. | C6: Cualitativo | D6: 1.5 | E6: Reputación Académica Externa | F6: Opinión de expertos externos sobre programas | G6: Rúbrica de evaluación de pares externos | H6: ≥4/5 | I6: Informes de evaluación externa | J6: Division of Academic Affairs | K6: Anual | L6: En levantamiento o pendiente de medición anual | M6: Avance del levantamiento / revisión de evidencia | N6: Emitir evaluación final anual
A7: 1. Portafolio Académico | B7: Establecer una comunidad de aprendizaje diversa y global, mediante programas académicos y de educación continua en diversos idiomas. | C7: Cuantitativo | D7: 1.6 | E7: Nº Programas Autorizados (CIE) | F7: Total de programas aprobados por regulador | G7: Conteo anual | H7: ≥11 | I7: Resoluciones CIE | J7: Division of Academic Affairs | K7: Anual | L7: En levantamiento o pendiente de medición anual | M7: Avance del levantamiento / revisión de evidencia | N7: Emitir evaluación final anual
A8: 1. Portafolio Académico | B8: Establecer una comunidad de aprendizaje diversa y global, mediante programas académicos y de educación continua en diversos idiomas. | C8: Cuantitativo | D8: 1.7 | E8: Graduation Rate General | F8: % estudiantes que se gradúan a tiempo | G8: (Graduados cohorte / ingresantes cohorte)×100 | H8: ≥70% | I8: Registros académicos | J8: Division of Student Services | K8: Anual | L8: En levantamiento o pendiente de medición anual | M8: Avance del levantamiento / revisión de evidencia | N8: Emitir evaluación final anual
A9: 1. Portafolio Académico | B9: Establecer una comunidad de aprendizaje diversa y global, mediante programas académicos y de educación continua en diversos idiomas. | C9: Cuantitativo | D9: 1.8 | E9: Retention Rate Estudiantil | F9: % estudiantes que permanecen activos | G9: [(Matriculados–Retirados)/Matriculados]×100 | H9: ≥85% | I9: Sistema académico (SMS) | J9: Division of Student Services | K9: Anual | L9: En levantamiento o pendiente de medición anual | M9: Avance del levantamiento / revisión de evidencia | N9: Emitir evaluación final anual
A10: 1. Portafolio Académico | B10: Establecer una comunidad de aprendizaje diversa y global, mediante programas académicos y de educación continua en diversos idiomas. | C10: Cuantitativo | D10: 1.9 | E10: Diversidad Geográfica | F10: Nº países representados en matrícula | G10: Conteo anual | H10: ≥20 países | I10: Registro de admisión | J10: Division of Admissions/Marketing | K10: Anual | L10: En levantamiento o pendiente de medición anual | M10: Avance del levantamiento / revisión de evidencia | N10: Emitir evaluación final anual
A11: 1. Portafolio Académico | B11: Establecer una comunidad de aprendizaje diversa y global, mediante programas académicos y de educación continua en diversos idiomas. | C11: Cuantitativo | D11: 1.10 | E11: Oferta Efectiva de Programas | F11: Programas activos/total de oferta | G11: (Programas activos / total) ×100 | H11: ≥59% | I11: Plan académico anual | J11: Division of Admissions/Marketing | K11: Anual | L11: En levantamiento o pendiente de medición anual | M11: Avance del levantamiento / revisión de evidencia | N11: Emitir evaluación final anual
A12: 2. Claustro Académico | B12: Mantener un claustro académico superior que proyecte calidad y solidez, mediante selección curada de profesores con experiencia internacional vigente, especialistas en su materia. | C12: Cualitativo | D12: 2.1 | E12: Evaluación Docente por Estudiantes | F12: Opinión estudiantil sobre docencia | G12: Encuesta final de curso | H12: ≥4/5 | I12: Encuestas institucionales | J12: Division of Student Services | K12: Mensual | L12: Analizar valor/tendencia acumulada hasta el corte | M12: Analizar valor/tendencia acumulada hasta el corte | N12: Analizar valor/tendencia acumulada hasta el corte
... A65: 7. Apoyo Económico | B65: Búsqueda constante de alternativas de acceso y apoyo a estudiantes y alumni, basada en mérito académico y alineamiento con la cultura BGU. | C65: Cuantitativo | D65: 7.10 | E65: Graduation Rate Becados | F65: Éxito de estudiantes con apoyo | G65: (Graduados becados/total becados)×100 | H65: ≥70% | I65: Registro académico | J65: Division of Student Services | K65: Anual | L65: En levantamiento o pendiente de medición anual | M65: Avance del levantamiento / revisión de evidencia | N65: Emitir evaluación final anual
